[
    {
        "PROD_PERM": 26,
        "RDNDISPLAY": 84,
        "DSPLY_NAME": "xlhbb",
        "TIMACT": "hellh",
        "NETCHNG_1": 0.2,
        "HIGH_1": 0.99,
        "LOW_1": 0.87,
        "CURRENCY": "oesok",
        "ACTIV_DATE": "snsxb",
        "OPEN_PRC": 0.48,
        "HST_CLOSE": 0.04,
        "BID": 0.63,
        "BID_1": 0.65,
        "BID_2": 0.98,
        "ASK": 0.27,
        "ASK_1": 0.56,
        "ASK_2": 0.81,
        "ACVOL_1": 100,
        "TRD_UNITS": "fstef",
        "PCTCHNG": 0.93,
        "OPEN_BID": 0.01,
        "OPEN_ASK": 0.61,
        "CLOSE_BID": 0.35,
        "CLOSE_ASK": 0.35,
        "NUM_MOVES": 45,
        "OFFCL_CODE": "tjdui",
        "HSTCLSDATE": "yconx",
        "YRHIGH": 0.54,
        "YRLOW": 0.04,
        "BCKGRNDPAG": "dving",
        "BID_NET_CH": 0.52,
        "BID_TICK_1": "efgve",
        "MID_PRICE": 0.63,
        "MID_NET_CH": 0.75,
        "MID_CLOSE": 0.18,
        "HIGHTP_1": "tvlbh",
        "LOWTP_1": "zuahu",
        "BID_HIGH_1": 0.09,
        "BID_LOW_1": 0.56,
        "YRBIDHIGH": 0.09,
        "YRBIDLOW": 0.74,
        "HST_CLSBID": 0.64,
        "HSTCLBDDAT": "qgeex",
        "NUM_BIDS": 8,
        "RECORDTYPE": 34,
        "ACT_TP_1": "vanhk",
        "ACT_TP_2": "zgaoe",
        "ACT_TP_3": "ckwfm",
        "SEC_ACT_1": 0.23,
        "SEC_ACT_2": 0.0,
        "SEC_ACT_3": 0.32,
        "SC_ACT_TP1": "ukkkp",
        "SC_ACT_TP2": "gwble",
        "SC_ACT_TP3": "hccjt",
        "OPEN_TIME": "vatae",
        "HIGH_TIME": "xeclc",
        "LOW_TIME": "zjdfa",
        "YRHIGHDAT": "vuuff",
        "YRLOWDAT": "gtpxi",
        "IRGPRC": 0.29,
        "TIMCOR": "qvvbr",
        "PRIMACT_1": 0.48,
        "PRIMACT_2": 0.87,
        "PRIMACT_3": 0.01,
        "BASE_CCY": "pmbvl",
        "BCAST_REF": "igmfv",
        "CROSS_SC": "seqln",
        "DLG_CODE1": "gjsqa",
        "DLG_CODE2": "kbcoo",
        "DLG_CODE3": "sbdxu",
        "CTBTR_1": "vyjhr",
        "CTBTR_2": "dpmzv",
        "CTBTR_3": "rrprb",
        "CTB_LOC1": "ekcbh",
        "CTB_LOC2": "azqyy",
        "CTB_LOC3": "pplou",
        "CTB_PAGE1": "uvptg",
        "CTB_PAGE2": "dnydx",
        "CTB_PAGE3": "yezbw",
        "VALUE_DT1": "lfkus",
        "VALUE_DT2": "cghst",
        "VALUE_DT3": "cuhxd",
        "SEC_HIGH": 0.3,
        "SEC_HI_TP": "qskmk",
        "SEC_LOW": 0.21,
        "SEC_LO_TP": "cjoge",
        "OPEN_TYPE": "qemkz",
        "CLOSE_TYPE": "ncnrw",
        "BKGD_REF": "cofob",
        "GEN_TEXT16": "evpeq",
        "GEN_VAL3": 0.96,
        "GEN_VAL4": 0.71,
        "GV1_TEXT": "keddj",
        "GV2_TEXT": "sxbvj",
        "GV4_TEXT": "ptngn",
        "VALUE_TS1": "fysdz",
        "VALUE_TS2": "tdtku",
        "VALUE_TS3": "pdiqz",
        "QUOTIM": "yoxgz",
        "GEN_VAL5": 0.4,
        "GEN_VAL6": 0.93,
        "GEN_VAL7": 0.8,
        "GEN_VAL8": 0.77,
        "GEN_VAL9": 0.14,
        "GEN_VAL10": 0.29,
        "GV5_TEXT": "psrkm",
        "GV6_TEXT": "mptmi",
        "GV7_TEXT": "lfwwf",
        "GV8_TEXT": "jfroa",
        "GV9_TEXT": "oluaj",
        "GV10_TEXT": "abphj",
        "GN_TXT16_2": "hcput",
        "GV1_TIME": "whuei",
        "PREF_DISP": 3,
        "GN_TXT24_1": "mqdux",
        "DSO_ID": 66,
        "RDN_EXCHD2": "zmjim",
        "PREV_DISP": 66,
        "ASIA_CL_DT": "qbwkr",
        "ASIA_CLOSE": 0.45,
        "ASIA_HI_TM": "xcaoh",
        "ASIA_HIGH": 0.82,
        "ASIA_LOW": 0.68,
        "ASIA_LW_TM": "llohu",
        "ASIA_NETCH": 0.76,
        "ASIA_OP_TM": "esvqn",
        "ASIA_OPEN": 0.54,
        "EURO_CL_DT": "exttn",
        "EURO_CLOSE": 0.3,
        "EURO_HI_TM": "evjlo",
        "EURO_HIGH": 0.53,
        "EURO_LOW": 0.09,
        "EURO_LW_TM": "tspab",
        "EURO_NETCH": 0.73,
        "EURO_OP_TM": "podtt",
        "EURO_OPEN": 1.0,
        "US_CL_DT": "qxmzb",
        "US_CLOSE": 0.83,
        "US_HI_TM": "igfmj",
        "US_HIGH": 0.07,
        "US_LOW": 0.36,
        "US_LW_TM": "jpoka",
        "US_NETCH": 0.94,
        "US_OP_TM": "kihon",
        "US_OPEN": 0.36,
        "ASK_SPREAD": 0.61,
        "BID_SPREAD": 0.91,
        "MID_SPREAD": 0.63,
        "MONTH_HIGH": 0.98,
        "MONTH_LOW": 0.79,
        "PCTCHG_3M": 0.08,
        "PCTCHG_6M": 0.3,
        "PCTCHG_MTD": 0.63,
        "PCTCHG_YTD": 0.96,
        "QUOTE_DATE": "ifqgj",
        "WEEK_HIGH": 0.26,
        "WEEK_LOW": 0.63,
        "ASK_HIGH_1": 0.67,
        "ASK_HI_TME": "pfuas",
        "ASK_LOW_1": 0.9,
        "ASK_LO_TME": "juela",
        "BID_ASK_DT": "lypji",
        "HIGH_2": 0.7,
        "HIGH_3": 0.86,
        "HIGH_4": 0.67,
        "HIGH_5": 0.21,
        "HIGH_TIME2": "bxiyw",
        "HIGH_TIME3": "hcocc",
        "HIGH_TIME4": "swevg",
        "HIGH_TIME5": "xozlx",
        "LOW_2": 0.82,
        "LOW_3": 0.71,
        "LOW_4": 0.13,
        "LOW_5": 0.4,
        "LOW_TIME2": "mihkp",
        "LOW_TIME3": "jyeoz",
        "LOW_TIME4": "crlal",
        "LOW_TIME5": "uddtp",
        "SCALING": "zxahm",
        "START_DT": "rrzmo",
        "WKHI_DT": "yeade",
        "WKLO_DT": "mgrri",
        "MTHHI_DT": "hjrzn",
        "MTHLO_DT": "rmlqy",
        "QUOTIM_MS": 28,
        "MID_HIGH": 0.23,
        "MID_LOW": 0.3,
        "MID_HTIM": "hdwnq",
        "MID_LTIM": "inupg",
        "MID_OPEN": 0.05,
        "CONTEXT_ID": 51,
        "BID_HIGH_2": 0.52,
        "BID_HIGH_3": 0.31,
        "BID_HIGH_4": 0.19,
        "BID_HIGH_5": 0.35,
        "BID_LOW_2": 0.35,
        "BID_LOW_3": 0.29,
        "BID_LOW_4": 0.16,
        "BID_LOW_5": 0.11,
        "ASK_HIGH_2": 0.54,
        "ASK_HIGH_3": 0.66,
        "ASK_HIGH_4": 0.45,
        "ASK_HIGH_5": 0.6,
        "ASK_LOW_2": 0.17,
        "ASK_LOW_3": 0.06,
        "ASK_LOW_4": 0.63,
        "ASK_LOW_5": 0.41,
        "PRV_BID_H": 0.67,
        "PRV_ASK_H": 0.61,
        "PRV_BID_L": 0.46,
        "PRV_ASK_L": 0.42,
        "DDS_DSO_ID": 94,
        "BR_LINK1": null,
        "BR_LINK2": null,
        "BR_LINK3": null,
        "SPS_SP_RIC": "gjabm",
        "QUOTIM_2": "jgxoo",
        "QUOTIM_3": "uxemy",
        "QUOTE_DT2": "glmek",
        "QUOTE_DT3": "pooyr",
        "ASKYRHIDAT": "wftqu",
        "ASKYRLODAT": "gdlyw",
        "BIDYRHIDAT": "vyvfe",
        "BIDYRLODAT": "towdb",
        "ASIABAC_DT": "mnkwa",
        "EUBAC_DT": "cppls",
        "USBAC_DT": "awctc",
        "HST_NUMBID": 24,
        "ASK_FWDOR": null,
        "BID_FWDOR": null,
        "AMERCL_ASK": 0.14,
        "AMERCL_BID": 0.59,
        "AMERHI_ASK": 0.62,
        "AMERHI_BID": 0.9,
        "AMERLO_ASK": 0.92,
        "AMERLO_BID": 0.4,
        "AMEROP_ASK": 0.67,
        "AMEROP_BID": 0.01,
        "ASIACL_ASK": 0.57,
        "ASIACL_BID": 0.0,
        "ASIAHI_ASK": 0.85,
        "ASIAHI_BID": 0.87,
        "ASIALO_ASK": 0.67,
        "ASIALO_BID": 0.45,
        "ASIAOP_ASK": 0.78,
        "ASIAOP_BID": 0.46,
        "BIDPCTCHNG": 0.15,
        "EURCL_ASK": 0.77,
        "EURCL_BID": 0.09,
        "EURHI_ASK": 0.04,
        "EURHI_BID": 0.19,
        "EURLO_ASK": 0.77,
        "EURLO_BID": 0.6,
        "EUROP_ASK": 0.95,
        "EUROP_BID": 0.81,
        "HST_HIMID": 0.41,
        "HST_LOMID": 0.16,
        "HST_OPNASK": 0.54,
        "HST_OPNBID": 0.26,
        "YRASKHIGH": 0.97,
        "YRASKLOW": 0.13,
        "ASIA_BNC": 0.63,
        "EURO_BNC": 0.26,
        "MTH_ASK_LO": 0.91,
        "MTH_BID_HI": 0.11,
        "US_BNC": 0.32,
        "WK_ASK_LO": 0.17,
        "WK_BID_HI": 0.33,
        "BID_HOURLY": 0.12,
        "RCS_AS_CL2": "rucnm",
        "MTH_ALO_DT": "hvjlj",
        "MTH_BHI_DT": "cyidl",
        "WK_ALO_DT": "dmtwu",
        "WK_BHI_DT": "olmco",
        "FXMM_TYPE": "hofwi",
        "ASIA_AH_MS": "vkwdp",
        "ASIA_AL_MS": "scras",
        "ASIA_AO_MS": "lmzgl",
        "ASIA_BH_MS": "nausb",
        "ASIA_BL_MS": "luysw",
        "ASIA_BO_MS": "idigt",
        "EURO_AH_MS": "mcbfn",
        "EURO_AL_MS": "loukk",
        "EURO_AO_MS": "eggor",
        "EURO_BH_MS": "pyccx",
        "EURO_BL_MS": "znvbo",
        "EURO_BO_MS": "uextc",
        "US_AH_MS": "zlopv",
        "US_AL_MS": "fbklx",
        "US_AO_MS": "bwlds",
        "US_BH_MS": "bwlry",
        "US_BL_MS": "rgmhq",
        "US_BO_MS": "ucbuj",
        "OPN_BID_MS": "uwegg",
        "ASKHI1_MS": "jnmqt",
        "ASKHI2_MS": "sitqi",
        "ASKHI3_MS": "lunsv",
        "ASKHI4_MS": "wmklz",
        "ASKHI5_MS": "wiydi",
        "ASKLO1_MS": "kvhim",
        "ASKLO2_MS": "nhswr",
        "ASKLO3_MS": "omrod",
        "ASKLO4_MS": "nlpce",
        "ASKLO5_MS": "rtnpc",
        "BIDHI1_MS": "kijmi",
        "BIDHI2_MS": "spavb",
        "BIDHI3_MS": "zbocn",
        "BIDHI4_MS": "deuud",
        "BIDHI5_MS": "vvtci",
        "BIDLO1_MS": "jlclv",
        "BIDLO2_MS": "dhxcn",
        "BIDLO3_MS": "hdfzz",
        "BIDLO4_MS": "zqkxc",
        "BIDLO5_MS": "obsel",
        "MIDHI1_MS": "szrdn",
        "MIDLO1_MS": "oswtq",
        "BID_HR_MS": "jwuti"
    },
    {
        "PROD_PERM": 19,
        "RDNDISPLAY": 46,
        "DSPLY_NAME": "sinpf",
        "TIMACT": "vuciu",
        "NETCHNG_1": 0.99,
        "HIGH_1": 0.75,
        "LOW_1": 0.74,
        "CURRENCY": "cbqmf",
        "ACTIV_DATE": "fqaey",
        "OPEN_PRC": 0.62,
        "HST_CLOSE": 0.57,
        "BID": 0.01,
        "BID_1": 0.71,
        "BID_2": 0.26,
        "ASK": 0.13,
        "ASK_1": 0.31,
        "ASK_2": 0.67,
        "ACVOL_1": 57,
        "TRD_UNITS": "nwqou",
        "PCTCHNG": 0.47,
        "OPEN_BID": 0.63,
        "OPEN_ASK": 0.82,
        "CLOSE_BID": 0.71,
        "CLOSE_ASK": 0.4,
        "NUM_MOVES": 28,
        "OFFCL_CODE": "ixvem",
        "HSTCLSDATE": "notjc",
        "YRHIGH": 0.4,
        "YRLOW": 0.12,
        "BCKGRNDPAG": "valsp",
        "BID_NET_CH": 0.36,
        "BID_TICK_1": "lqban",
        "MID_PRICE": 0.91,
        "MID_NET_CH": 0.7,
        "MID_CLOSE": 0.53,
        "HIGHTP_1": "kookl",
        "LOWTP_1": "uoesz",
        "BID_HIGH_1": 0.55,
        "BID_LOW_1": 0.73,
        "YRBIDHIGH": 0.6,
        "YRBIDLOW": 0.62,
        "HST_CLSBID": 0.36,
        "HSTCLBDDAT": "ghwjs",
        "NUM_BIDS": 74,
        "RECORDTYPE": 78,
        "ACT_TP_1": "zoxep",
        "ACT_TP_2": "ddpwp",
        "ACT_TP_3": "pdpkd",
        "SEC_ACT_1": 0.32,
        "SEC_ACT_2": 0.17,
        "SEC_ACT_3": 0.92,
        "SC_ACT_TP1": "heifg",
        "SC_ACT_TP2": "fiirh",
        "SC_ACT_TP3": "rsfts",
        "OPEN_TIME": "cxsej",
        "HIGH_TIME": "qxdag",
        "LOW_TIME": "sfcry",
        "YRHIGHDAT": "pcarv",
        "YRLOWDAT": "ofvku",
        "IRGPRC": 0.18,
        "TIMCOR": "fmnnm",
        "PRIMACT_1": 0.5,
        "PRIMACT_2": 0.24,
        "PRIMACT_3": 0.35,
        "BASE_CCY": "ekbxi",
        "BCAST_REF": "qnnbk",
        "CROSS_SC": "sokdc",
        "DLG_CODE1": "claok",
        "DLG_CODE2": "txyzp",
        "DLG_CODE3": "xrzgf",
        "CTBTR_1": "auipc",
        "CTBTR_2": "qgyzo",
        "CTBTR_3": "bwiow",
        "CTB_LOC1": "arenv",
        "CTB_LOC2": "pogdw",
        "CTB_LOC3": "yqotn",
        "CTB_PAGE1": "vdrez",
        "CTB_PAGE2": "xokym",
        "CTB_PAGE3": "ljhcx",
        "VALUE_DT1": "bbobx",
        "VALUE_DT2": "cdvha",
        "VALUE_DT3": "mfjfh",
        "SEC_HIGH": 0.19,
        "SEC_HI_TP": "yzink",
        "SEC_LOW": 0.21,
        "SEC_LO_TP": "owlmy",
        "OPEN_TYPE": "cztjw",
        "CLOSE_TYPE": "iqfjm",
        "BKGD_REF": "icpal",
        "GEN_TEXT16": "lifbp",
        "GEN_VAL3": 0.19,
        "GEN_VAL4": 0.38,
        "GV1_TEXT": "nlceq",
        "GV2_TEXT": "ersnh",
        "GV4_TEXT": "whyzx",
        "VALUE_TS1": "hubbk",
        "VALUE_TS2": "fjfaw",
        "VALUE_TS3": "zrmpt",
        "QUOTIM": "poiut",
        "GEN_VAL5": 0.27,
        "GEN_VAL6": 0.83,
        "GEN_VAL7": 0.84,
        "GEN_VAL8": 0.12,
        "GEN_VAL9": 0.41,
        "GEN_VAL10": 0.43,
        "GV5_TEXT": "djgwn",
        "GV6_TEXT": "mxgnf",
        "GV7_TEXT": "exkck",
        "GV8_TEXT": "omfvo",
        "GV9_TEXT": "lzjnw",
        "GV10_TEXT": "wjtkt",
        "GN_TXT16_2": "esqdi",
        "GV1_TIME": "vwmmv",
        "PREF_DISP": 86,
        "GN_TXT24_1": "wsyva",
        "DSO_ID": 87,
        "RDN_EXCHD2": "mltfh",
        "PREV_DISP": 12,
        "ASIA_CL_DT": "mbbrj",
        "ASIA_CLOSE": 0.98,
        "ASIA_HI_TM": "epxno",
        "ASIA_HIGH": 0.91,
        "ASIA_LOW": 0.78,
        "ASIA_LW_TM": "uazed",
        "ASIA_NETCH": 0.6,
        "ASIA_OP_TM": "osnwm",
        "ASIA_OPEN": 0.4,
        "EURO_CL_DT": "blerf",
        "EURO_CLOSE": 0.15,
        "EURO_HI_TM": "oaprz",
        "EURO_HIGH": 0.03,
        "EURO_LOW": 0.4,
        "EURO_LW_TM": "egims",
        "EURO_NETCH": 0.56,
        "EURO_OP_TM": "rmhyj",
        "EURO_OPEN": 0.87,
        "US_CL_DT": "rrdhe",
        "US_CLOSE": 0.87,
        "US_HI_TM": "kitfb",
        "US_HIGH": 0.8,
        "US_LOW": 0.52,
        "US_LW_TM": "stuir",
        "US_NETCH": 0.59,
        "US_OP_TM": "erlyg",
        "US_OPEN": 0.71,
        "ASK_SPREAD": 0.98,
        "BID_SPREAD": 0.57,
        "MID_SPREAD": 0.47,
        "MONTH_HIGH": 0.33,
        "MONTH_LOW": 0.22,
        "PCTCHG_3M": 0.04,
        "PCTCHG_6M": 0.67,
        "PCTCHG_MTD": 0.65,
        "PCTCHG_YTD": 0.55,
        "QUOTE_DATE": "bonsc",
        "WEEK_HIGH": 0.56,
        "WEEK_LOW": 0.75,
        "ASK_HIGH_1": 0.93,
        "ASK_HI_TME": "jebfs",
        "ASK_LOW_1": 0.09,
        "ASK_LO_TME": "kybkh",
        "BID_ASK_DT": "wtxfi",
        "HIGH_2": 0.83,
        "HIGH_3": 0.58,
        "HIGH_4": 0.31,
        "HIGH_5": 0.74,
        "HIGH_TIME2": "twuqd",
        "HIGH_TIME3": "poznc",
        "HIGH_TIME4": "issmw",
        "HIGH_TIME5": "rzscr",
        "LOW_2": 0.41,
        "LOW_3": 0.79,
        "LOW_4": 0.63,
        "LOW_5": 0.77,
        "LOW_TIME2": "ftzcx",
        "LOW_TIME3": "svert",
        "LOW_TIME4": "cbsgw",
        "LOW_TIME5": "dogpd",
        "SCALING": "qgbnd",
        "START_DT": "rmjjf",
        "WKHI_DT": "sokne",
        "WKLO_DT": "zprsk",
        "MTHHI_DT": "pjlyq",
        "MTHLO_DT": "rhowc",
        "QUOTIM_MS": 6,
        "MID_HIGH": 0.52,
        "MID_LOW": 0.68,
        "MID_HTIM": "nauhc",
        "MID_LTIM": "eyxeq",
        "MID_OPEN": 0.42,
        "CONTEXT_ID": 31,
        "BID_HIGH_2": 0.17,
        "BID_HIGH_3": 0.96,
        "BID_HIGH_4": 0.18,
        "BID_HIGH_5": 0.53,
        "BID_LOW_2": 0.51,
        "BID_LOW_3": 0.37,
        "BID_LOW_4": 0.4,
        "BID_LOW_5": 0.1,
        "ASK_HIGH_2": 0.18,
        "ASK_HIGH_3": 0.69,
        "ASK_HIGH_4": 0.3,
        "ASK_HIGH_5": 0.73,
        "ASK_LOW_2": 0.71,
        "ASK_LOW_3": 0.63,
        "ASK_LOW_4": 0.65,
        "ASK_LOW_5": 0.99,
        "PRV_BID_H": 0.06,
        "PRV_ASK_H": 0.71,
        "PRV_BID_L": 0.19,
        "PRV_ASK_L": 0.31,
        "DDS_DSO_ID": 69,
        "BR_LINK1": null,
        "BR_LINK2": null,
        "BR_LINK3": null,
        "SPS_SP_RIC": "eweas",
        "QUOTIM_2": "genpe",
        "QUOTIM_3": "czhsb",
        "QUOTE_DT2": "hoiol",
        "QUOTE_DT3": "agtsn",
        "ASKYRHIDAT": "ouchg",
        "ASKYRLODAT": "ehgec",
        "BIDYRHIDAT": "qznju",
        "BIDYRLODAT": "penme",
        "ASIABAC_DT": "vyowf",
        "EUBAC_DT": "apxsx",
        "USBAC_DT": "gcutx",
        "HST_NUMBID": 8,
        "ASK_FWDOR": null,
        "BID_FWDOR": null,
        "AMERCL_ASK": 0.72,
        "AMERCL_BID": 0.4,
        "AMERHI_ASK": 0.24,
        "AMERHI_BID": 0.11,
        "AMERLO_ASK": 0.56,
        "AMERLO_BID": 0.32,
        "AMEROP_ASK": 0.67,
        "AMEROP_BID": 0.11,
        "ASIACL_ASK": 0.61,
        "ASIACL_BID": 0.16,
        "ASIAHI_ASK": 0.72,
        "ASIAHI_BID": 0.26,
        "ASIALO_ASK": 0.09,
        "ASIALO_BID": 0.24,
        "ASIAOP_ASK": 0.5,
        "ASIAOP_BID": 0.01,
        "BIDPCTCHNG": 0.18,
        "EURCL_ASK": 0.07,
        "EURCL_BID": 0.34,
        "EURHI_ASK": 0.19,
        "EURHI_BID": 0.59,
        "EURLO_ASK": 0.44,
        "EURLO_BID": 0.71,
        "EUROP_ASK": 0.08,
        "EUROP_BID": 0.6,
        "HST_HIMID": 0.92,
        "HST_LOMID": 0.78,
        "HST_OPNASK": 0.7,
        "HST_OPNBID": 0.04,
        "YRASKHIGH": 0.97,
        "YRASKLOW": 0.75,
        "ASIA_BNC": 0.05,
        "EURO_BNC": 0.67,
        "MTH_ASK_LO": 0.23,
        "MTH_BID_HI": 0.52,
        "US_BNC": 0.97,
        "WK_ASK_LO": 0.17,
        "WK_BID_HI": 0.99,
        "BID_HOURLY": 0.77,
        "RCS_AS_CL2": "txrdn",
        "MTH_ALO_DT": "clmyx",
        "MTH_BHI_DT": "bvoub",
        "WK_ALO_DT": "nbisv",
        "WK_BHI_DT": "fqlkp",
        "FXMM_TYPE": "dmbyn",
        "ASIA_AH_MS": "zcmmb",
        "ASIA_AL_MS": "zwgks",
        "ASIA_AO_MS": "twuvg",
        "ASIA_BH_MS": "knbvy",
        "ASIA_BL_MS": "afkqg",
        "ASIA_BO_MS": "slyrr",
        "EURO_AH_MS": "hyvyi",
        "EURO_AL_MS": "ctqqs",
        "EURO_AO_MS": "jbhst",
        "EURO_BH_MS": "vwcgx",
        "EURO_BL_MS": "sztzc",
        "EURO_BO_MS": "wnvnb",
        "US_AH_MS": "rmwvu",
        "US_AL_MS": "iccjx",
        "US_AO_MS": "jtpoq",
        "US_BH_MS": "rucxc",
        "US_BL_MS": "lbrpb",
        "US_BO_MS": "ngelh",
        "OPN_BID_MS": "ngoki",
        "ASKHI1_MS": "ubsyj",
        "ASKHI2_MS": "aefyv",
        "ASKHI3_MS": "yrejn",
        "ASKHI4_MS": "cycgh",
        "ASKHI5_MS": "tpkqo",
        "ASKLO1_MS": "rhiuf",
        "ASKLO2_MS": "ugfkw",
        "ASKLO3_MS": "nbrzg",
        "ASKLO4_MS": "glywt",
        "ASKLO5_MS": "zawvz",
        "BIDHI1_MS": "bubiv",
        "BIDHI2_MS": "nshua",
        "BIDHI3_MS": "imvtb",
        "BIDHI4_MS": "zuvlr",
        "BIDHI5_MS": "nazkz",
        "BIDLO1_MS": "iizpa",
        "BIDLO2_MS": "jgcby",
        "BIDLO3_MS": "vzfik",
        "BIDLO4_MS": "tkjfj",
        "BIDLO5_MS": "fbjgb",
        "MIDHI1_MS": "hwpiv",
        "MIDLO1_MS": "mfpkb",
        "BID_HR_MS": "qzlht"
    },
    {
        "PROD_PERM": 6,
        "RDNDISPLAY": 27,
        "DSPLY_NAME": "eumdm",
        "TIMACT": "evimb",
        "NETCHNG_1": 0.43,
        "HIGH_1": 0.82,
        "LOW_1": 0.05,
        "CURRENCY": "guspj",
        "ACTIV_DATE": "bargk",
        "OPEN_PRC": 0.85,
        "HST_CLOSE": 0.79,
        "BID": 0.16,
        "BID_1": 0.2,
        "BID_2": 0.66,
        "ASK": 0.57,
        "ASK_1": 0.38,
        "ASK_2": 1.0,
        "ACVOL_1": 64,
        "TRD_UNITS": "gxtax",
        "PCTCHNG": 0.48,
        "OPEN_BID": 0.63,
        "OPEN_ASK": 0.61,
        "CLOSE_BID": 0.9,
        "CLOSE_ASK": 0.8,
        "NUM_MOVES": 44,
        "OFFCL_CODE": "swhmy",
        "HSTCLSDATE": "dezjk",
        "YRHIGH": 0.18,
        "YRLOW": 0.01,
        "BCKGRNDPAG": "twzyr",
        "BID_NET_CH": 0.66,
        "BID_TICK_1": "rphxr",
        "MID_PRICE": 0.24,
        "MID_NET_CH": 0.57,
        "MID_CLOSE": 0.22,
        "HIGHTP_1": "zymkn",
        "LOWTP_1": "pxcnf",
        "BID_HIGH_1": 0.79,
        "BID_LOW_1": 0.45,
        "YRBIDHIGH": 0.48,
        "YRBIDLOW": 0.91,
        "HST_CLSBID": 0.27,
        "HSTCLBDDAT": "kmhnf",
        "NUM_BIDS": 57,
        "RECORDTYPE": 20,
        "ACT_TP_1": "dnpco",
        "ACT_TP_2": "klxia",
        "ACT_TP_3": "zkbdr",
        "SEC_ACT_1": 0.71,
        "SEC_ACT_2": 0.65,
        "SEC_ACT_3": 0.82,
        "SC_ACT_TP1": "cmlah",
        "SC_ACT_TP2": "twypq",
        "SC_ACT_TP3": "kejjc",
        "OPEN_TIME": "foaiy",
        "HIGH_TIME": "laggm",
        "LOW_TIME": "pwmgz",
        "YRHIGHDAT": "txuiw",
        "YRLOWDAT": "rmzsk",
        "IRGPRC": 0.42,
        "TIMCOR": "moyfu",
        "PRIMACT_1": 0.22,
        "PRIMACT_2": 0.64,
        "PRIMACT_3": 0.7,
        "BASE_CCY": "ozbbm",
        "BCAST_REF": "urbkb",
        "CROSS_SC": "cuvzv",
        "DLG_CODE1": "gqwsh",
        "DLG_CODE2": "gloqm",
        "DLG_CODE3": "ngbhu",
        "CTBTR_1": "xrowo",
        "CTBTR_2": "fcguy",
        "CTBTR_3": "ptgtz",
        "CTB_LOC1": "mrlgx",
        "CTB_LOC2": "rvyza",
        "CTB_LOC3": "txjwf",
        "CTB_PAGE1": "dllyp",
        "CTB_PAGE2": "jamjn",
        "CTB_PAGE3": "zsdzn",
        "VALUE_DT1": "gmjiv",
        "VALUE_DT2": "vofmz",
        "VALUE_DT3": "aklax",
        "SEC_HIGH": 0.8,
        "SEC_HI_TP": "fzmjb",
        "SEC_LOW": 0.33,
        "SEC_LO_TP": "qkouf",
        "OPEN_TYPE": "rslpb",
        "CLOSE_TYPE": "cjjsn",
        "BKGD_REF": "kdbzh",
        "GEN_TEXT16": "yawvk",
        "GEN_VAL3": 0.12,
        "GEN_VAL4": 0.97,
        "GV1_TEXT": "xfdua",
        "GV2_TEXT": "tajzx",
        "GV4_TEXT": "iglgw",
        "VALUE_TS1": "yyrpi",
        "VALUE_TS2": "tabea",
        "VALUE_TS3": "cdyqb",
        "QUOTIM": "whgcz",
        "GEN_VAL5": 0.89,
        "GEN_VAL6": 0.48,
        "GEN_VAL7": 0.17,
        "GEN_VAL8": 0.61,
        "GEN_VAL9": 0.89,
        "GEN_VAL10": 0.04,
        "GV5_TEXT": "uckbt",
        "GV6_TEXT": "wbosl",
        "GV7_TEXT": "ujqnn",
        "GV8_TEXT": "mpbiy",
        "GV9_TEXT": "mduce",
        "GV10_TEXT": "agwdh",
        "GN_TXT16_2": "onhme",
        "GV1_TIME": "nybqv",
        "PREF_DISP": 46,
        "GN_TXT24_1": "uesgv",
        "DSO_ID": 90,
        "RDN_EXCHD2": "zmnls",
        "PREV_DISP": 67,
        "ASIA_CL_DT": "fgfmi",
        "ASIA_CLOSE": 0.16,
        "ASIA_HI_TM": "siyvo",
        "ASIA_HIGH": 0.16,
        "ASIA_LOW": 0.03,
        "ASIA_LW_TM": "fpdzb",
        "ASIA_NETCH": 0.64,
        "ASIA_OP_TM": "ovrsz",
        "ASIA_OPEN": 0.31,
        "EURO_CL_DT": "mfuvm",
        "EURO_CLOSE": 0.31,
        "EURO_HI_TM": "rhavl",
        "EURO_HIGH": 0.31,
        "EURO_LOW": 0.86,
        "EURO_LW_TM": "jpuru",
        "EURO_NETCH": 0.91,
        "EURO_OP_TM": "ijxkv",
        "EURO_OPEN": 0.17,
        "US_CL_DT": "sexuc",
        "US_CLOSE": 0.29,
        "US_HI_TM": "lexxq",
        "US_HIGH": 0.31,
        "US_LOW": 0.07,
        "US_LW_TM": "fgqat",
        "US_NETCH": 0.21,
        "US_OP_TM": "lyaqe",
        "US_OPEN": 0.68,
        "ASK_SPREAD": 0.32,
        "BID_SPREAD": 0.91,
        "MID_SPREAD": 0.28,
        "MONTH_HIGH": 1.0,
        "MONTH_LOW": 0.34,
        "PCTCHG_3M": 0.44,
        "PCTCHG_6M": 0.79,
        "PCTCHG_MTD": 0.72,
        "PCTCHG_YTD": 0.26,
        "QUOTE_DATE": "cdoen",
        "WEEK_HIGH": 0.46,
        "WEEK_LOW": 0.23,
        "ASK_HIGH_1": 0.08,
        "ASK_HI_TME": "qjqfi",
        "ASK_LOW_1": 0.08,
        "ASK_LO_TME": "ptyiz",
        "BID_ASK_DT": "uydax",
        "HIGH_2": 0.13,
        "HIGH_3": 0.56,
        "HIGH_4": 0.2,
        "HIGH_5": 0.8,
        "HIGH_TIME2": "yscgm",
        "HIGH_TIME3": "fmzpt",
        "HIGH_TIME4": "khaae",
        "HIGH_TIME5": "bnffv",
        "LOW_2": 0.31,
        "LOW_3": 0.47,
        "LOW_4": 0.55,
        "LOW_5": 0.86,
        "LOW_TIME2": "jgylb",
        "LOW_TIME3": "vqxwu",
        "LOW_TIME4": "kuvoc",
        "LOW_TIME5": "eeyej",
        "SCALING": "rnubx",
        "START_DT": "ayjnm",
        "WKHI_DT": "pekrs",
        "WKLO_DT": "hhaod",
        "MTHHI_DT": "mtbez",
        "MTHLO_DT": "slcok",
        "QUOTIM_MS": 90,
        "MID_HIGH": 0.57,
        "MID_LOW": 0.58,
        "MID_HTIM": "dwczs",
        "MID_LTIM": "htlci",
        "MID_OPEN": 0.91,
        "CONTEXT_ID": 77,
        "BID_HIGH_2": 0.88,
        "BID_HIGH_3": 0.26,
        "BID_HIGH_4": 0.63,
        "BID_HIGH_5": 0.11,
        "BID_LOW_2": 0.35,
        "BID_LOW_3": 0.49,
        "BID_LOW_4": 0.13,
        "BID_LOW_5": 0.25,
        "ASK_HIGH_2": 0.77,
        "ASK_HIGH_3": 0.36,
        "ASK_HIGH_4": 0.96,
        "ASK_HIGH_5": 0.04,
        "ASK_LOW_2": 0.67,
        "ASK_LOW_3": 0.96,
        "ASK_LOW_4": 0.31,
        "ASK_LOW_5": 0.36,
        "PRV_BID_H": 0.41,
        "PRV_ASK_H": 0.99,
        "PRV_BID_L": 0.45,
        "PRV_ASK_L": 0.16,
        "DDS_DSO_ID": 30,
        "BR_LINK1": null,
        "BR_LINK2": null,
        "BR_LINK3": null,
        "SPS_SP_RIC": "rayzh",
        "QUOTIM_2": "vvvli",
        "QUOTIM_3": "yfrte",
        "QUOTE_DT2": "gzubi",
        "QUOTE_DT3": "fixca",
        "ASKYRHIDAT": "cervl",
        "ASKYRLODAT": "jtrpl",
        "BIDYRHIDAT": "teaut",
        "BIDYRLODAT": "zhoye",
        "ASIABAC_DT": "qjdeo",
        "EUBAC_DT": "ybxhu",
        "USBAC_DT": "ftpxn",
        "HST_NUMBID": 4,
        "ASK_FWDOR": null,
        "BID_FWDOR": null,
        "AMERCL_ASK": 0.71,
        "AMERCL_BID": 0.96,
        "AMERHI_ASK": 0.9,
        "AMERHI_BID": 0.13,
        "AMERLO_ASK": 0.1,
        "AMERLO_BID": 0.39,
        "AMEROP_ASK": 0.52,
        "AMEROP_BID": 0.01,
        "ASIACL_ASK": 0.22,
        "ASIACL_BID": 0.75,
        "ASIAHI_ASK": 0.75,
        "ASIAHI_BID": 0.3,
        "ASIALO_ASK": 0.64,
        "ASIALO_BID": 0.52,
        "ASIAOP_ASK": 0.9,
        "ASIAOP_BID": 0.19,
        "BIDPCTCHNG": 0.11,
        "EURCL_ASK": 0.37,
        "EURCL_BID": 0.99,
        "EURHI_ASK": 0.58,
        "EURHI_BID": 0.38,
        "EURLO_ASK": 0.79,
        "EURLO_BID": 0.45,
        "EUROP_ASK": 0.24,
        "EUROP_BID": 0.22,
        "HST_HIMID": 0.56,
        "HST_LOMID": 0.68,
        "HST_OPNASK": 0.05,
        "HST_OPNBID": 0.11,
        "YRASKHIGH": 0.36,
        "YRASKLOW": 0.4,
        "ASIA_BNC": 0.35,
        "EURO_BNC": 0.29,
        "MTH_ASK_LO": 0.77,
        "MTH_BID_HI": 0.07,
        "US_BNC": 0.62,
        "WK_ASK_LO": 0.5,
        "WK_BID_HI": 0.15,
        "BID_HOURLY": 0.8,
        "RCS_AS_CL2": "gckbd",
        "MTH_ALO_DT": "fpnhs",
        "MTH_BHI_DT": "ebcnd",
        "WK_ALO_DT": "qarnd",
        "WK_BHI_DT": "hktvf",
        "FXMM_TYPE": "dyaew",
        "ASIA_AH_MS": "xhxeq",
        "ASIA_AL_MS": "crmrm",
        "ASIA_AO_MS": "wejtu",
        "ASIA_BH_MS": "tfddc",
        "ASIA_BL_MS": "ddcgj",
        "ASIA_BO_MS": "xbwsf",
        "EURO_AH_MS": "mczic",
        "EURO_AL_MS": "vucpe",
        "EURO_AO_MS": "mzqlg",
        "EURO_BH_MS": "nzvgc",
        "EURO_BL_MS": "xztox",
        "EURO_BO_MS": "vgklf",
        "US_AH_MS": "jkxuo",
        "US_AL_MS": "itjwf",
        "US_AO_MS": "yyfdn",
        "US_BH_MS": "tvbxo",
        "US_BL_MS": "mffgm",
        "US_BO_MS": "qteqp",
        "OPN_BID_MS": "rtjqj",
        "ASKHI1_MS": "fkpan",
        "ASKHI2_MS": "veyjw",
        "ASKHI3_MS": "egocf",
        "ASKHI4_MS": "yckln",
        "ASKHI5_MS": "kznil",
        "ASKLO1_MS": "takqq",
        "ASKLO2_MS": "nwvfo",
        "ASKLO3_MS": "txwsd",
        "ASKLO4_MS": "xpspq",
        "ASKLO5_MS": "cghsv",
        "BIDHI1_MS": "laqzi",
        "BIDHI2_MS": "qiwux",
        "BIDHI3_MS": "dzlva",
        "BIDHI4_MS": "pqxex",
        "BIDHI5_MS": "ulbqi",
        "BIDLO1_MS": "kktgh",
        "BIDLO2_MS": "zbqam",
        "BIDLO3_MS": "wbnlx",
        "BIDLO4_MS": "qwfse",
        "BIDLO5_MS": "rarns",
        "MIDHI1_MS": "rtdor",
        "MIDLO1_MS": "roqrg",
        "BID_HR_MS": "wxuez"
    },
    {
        "PROD_PERM": 64,
        "RDNDISPLAY": 85,
        "DSPLY_NAME": "hltcx",
        "TIMACT": "gkseu",
        "NETCHNG_1": 0.62,
        "HIGH_1": 0.35,
        "LOW_1": 0.31,
        "CURRENCY": "xdcwa",
        "ACTIV_DATE": "ifzzx",
        "OPEN_PRC": 0.55,
        "HST_CLOSE": 0.53,
        "BID": 0.63,
        "BID_1": 0.94,
        "BID_2": 0.6,
        "ASK": 0.55,
        "ASK_1": 0.05,
        "ASK_2": 0.49,
        "ACVOL_1": 11,
        "TRD_UNITS": "weoja",
        "PCTCHNG": 0.8,
        "OPEN_BID": 1.0,
        "OPEN_ASK": 0.05,
        "CLOSE_BID": 0.9,
        "CLOSE_ASK": 0.87,
        "NUM_MOVES": 65,
        "OFFCL_CODE": "grjuo",
        "HSTCLSDATE": "tuqya",
        "YRHIGH": 0.28,
        "YRLOW": 0.43,
        "BCKGRNDPAG": "gusbb",
        "BID_NET_CH": 0.88,
        "BID_TICK_1": "kswwc",
        "MID_PRICE": 0.49,
        "MID_NET_CH": 0.57,
        "MID_CLOSE": 0.02,
        "HIGHTP_1": "saosg",
        "LOWTP_1": "lyfek",
        "BID_HIGH_1": 0.63,
        "BID_LOW_1": 0.17,
        "YRBIDHIGH": 0.1,
        "YRBIDLOW": 0.65,
        "HST_CLSBID": 0.49,
        "HSTCLBDDAT": "taonb",
        "NUM_BIDS": 3,
        "RECORDTYPE": 5,
        "ACT_TP_1": "xpubt",
        "ACT_TP_2": "ehazv",
        "ACT_TP_3": "lnpno",
        "SEC_ACT_1": 0.38,
        "SEC_ACT_2": 0.82,
        "SEC_ACT_3": 0.42,
        "SC_ACT_TP1": "owqmp",
        "SC_ACT_TP2": "ocixw",
        "SC_ACT_TP3": "avoex",
        "OPEN_TIME": "desvq",
        "HIGH_TIME": "cuaex",
        "LOW_TIME": "qoiqw",
        "YRHIGHDAT": "pdret",
        "YRLOWDAT": "duiha",
        "IRGPRC": 0.97,
        "TIMCOR": "dnziy",
        "PRIMACT_1": 0.85,
        "PRIMACT_2": 0.17,
        "PRIMACT_3": 0.13,
        "BASE_CCY": "gzpvc",
        "BCAST_REF": "smbfw",
        "CROSS_SC": "cmhga",
        "DLG_CODE1": "evubr",
        "DLG_CODE2": "fiqkb",
        "DLG_CODE3": "tbghe",
        "CTBTR_1": "qyqyq",
        "CTBTR_2": "bryrz",
        "CTBTR_3": "zldle",
        "CTB_LOC1": "hxcpm",
        "CTB_LOC2": "ybrjo",
        "CTB_LOC3": "tieaw",
        "CTB_PAGE1": "foknr",
        "CTB_PAGE2": "ampnn",
        "CTB_PAGE3": "eghyd",
        "VALUE_DT1": "mtsok",
        "VALUE_DT2": "dgntq",
        "VALUE_DT3": "ocqdy",
        "SEC_HIGH": 0.46,
        "SEC_HI_TP": "livhe",
        "SEC_LOW": 0.6,
        "SEC_LO_TP": "ifnkz",
        "OPEN_TYPE": "hnjqp",
        "CLOSE_TYPE": "tcvex",
        "BKGD_REF": "imsvd",
        "GEN_TEXT16": "dkiyk",
        "GEN_VAL3": 0.88,
        "GEN_VAL4": 0.41,
        "GV1_TEXT": "izlcv",
        "GV2_TEXT": "greeq",
        "GV4_TEXT": "swhmm",
        "VALUE_TS1": "skvot",
        "VALUE_TS2": "dpxzn",
        "VALUE_TS3": "dcziv",
        "QUOTIM": "rdlkj",
        "GEN_VAL5": 0.03,
        "GEN_VAL6": 0.62,
        "GEN_VAL7": 0.61,
        "GEN_VAL8": 0.1,
        "GEN_VAL9": 0.21,
        "GEN_VAL10": 0.66,
        "GV5_TEXT": "thupb",
        "GV6_TEXT": "esgoc",
        "GV7_TEXT": "rotnd",
        "GV8_TEXT": "fbhmy",
        "GV9_TEXT": "ykmtg",
        "GV10_TEXT": "bfvgc",
        "GN_TXT16_2": "dzlhj",
        "GV1_TIME": "ubadx",
        "PREF_DISP": 86,
        "GN_TXT24_1": "euafp",
        "DSO_ID": 38,
        "RDN_EXCHD2": "ttzpj",
        "PREV_DISP": 76,
        "ASIA_CL_DT": "gdlfs",
        "ASIA_CLOSE": 0.73,
        "ASIA_HI_TM": "qnytl",
        "ASIA_HIGH": 0.22,
        "ASIA_LOW": 0.35,
        "ASIA_LW_TM": "zrshd",
        "ASIA_NETCH": 0.31,
        "ASIA_OP_TM": "kihyd",
        "ASIA_OPEN": 0.06,
        "EURO_CL_DT": "fpquv",
        "EURO_CLOSE": 0.47,
        "EURO_HI_TM": "ezzpo",
        "EURO_HIGH": 0.58,
        "EURO_LOW": 0.91,
        "EURO_LW_TM": "tlusv",
        "EURO_NETCH": 0.11,
        "EURO_OP_TM": "gvdll",
        "EURO_OPEN": 0.87,
        "US_CL_DT": "kucvl",
        "US_CLOSE": 0.15,
        "US_HI_TM": "miqgv",
        "US_HIGH": 0.48,
        "US_LOW": 0.74,
        "US_LW_TM": "pnqdd",
        "US_NETCH": 0.52,
        "US_OP_TM": "qwnnp",
        "US_OPEN": 0.03,
        "ASK_SPREAD": 0.87,
        "BID_SPREAD": 0.44,
        "MID_SPREAD": 0.12,
        "MONTH_HIGH": 0.89,
        "MONTH_LOW": 0.6,
        "PCTCHG_3M": 0.27,
        "PCTCHG_6M": 0.99,
        "PCTCHG_MTD": 0.67,
        "PCTCHG_YTD": 0.58,
        "QUOTE_DATE": "bisft",
        "WEEK_HIGH": 0.58,
        "WEEK_LOW": 0.11,
        "ASK_HIGH_1": 0.12,
        "ASK_HI_TME": "ihobr",
        "ASK_LOW_1": 0.87,
        "ASK_LO_TME": "kikon",
        "BID_ASK_DT": "vjymd",
        "HIGH_2": 0.06,
        "HIGH_3": 0.43,
        "HIGH_4": 0.99,
        "HIGH_5": 0.03,
        "HIGH_TIME2": "zipwa",
        "HIGH_TIME3": "mieby",
        "HIGH_TIME4": "aiadu",
        "HIGH_TIME5": "xbgsw",
        "LOW_2": 0.28,
        "LOW_3": 0.54,
        "LOW_4": 0.43,
        "LOW_5": 0.48,
        "LOW_TIME2": "pbapi",
        "LOW_TIME3": "cziha",
        "LOW_TIME4": "edjwx",
        "LOW_TIME5": "scisf",
        "SCALING": "uxiff",
        "START_DT": "yyjpn",
        "WKHI_DT": "wbtev",
        "WKLO_DT": "gnttk",
        "MTHHI_DT": "ofufh",
        "MTHLO_DT": "zdmbm",
        "QUOTIM_MS": 56,
        "MID_HIGH": 0.9,
        "MID_LOW": 0.05,
        "MID_HTIM": "eqsqk",
        "MID_LTIM": "jtmxa",
        "MID_OPEN": 0.07,
        "CONTEXT_ID": 47,
        "BID_HIGH_2": 0.45,
        "BID_HIGH_3": 0.95,
        "BID_HIGH_4": 0.71,
        "BID_HIGH_5": 0.96,
        "BID_LOW_2": 0.2,
        "BID_LOW_3": 0.97,
        "BID_LOW_4": 0.16,
        "BID_LOW_5": 0.81,
        "ASK_HIGH_2": 0.19,
        "ASK_HIGH_3": 0.72,
        "ASK_HIGH_4": 0.65,
        "ASK_HIGH_5": 0.59,
        "ASK_LOW_2": 0.96,
        "ASK_LOW_3": 0.75,
        "ASK_LOW_4": 0.17,
        "ASK_LOW_5": 0.09,
        "PRV_BID_H": 0.12,
        "PRV_ASK_H": 0.53,
        "PRV_BID_L": 0.81,
        "PRV_ASK_L": 0.34,
        "DDS_DSO_ID": 74,
        "BR_LINK1": null,
        "BR_LINK2": null,
        "BR_LINK3": null,
        "SPS_SP_RIC": "nhxmq",
        "QUOTIM_2": "vwqpn",
        "QUOTIM_3": "cykxj",
        "QUOTE_DT2": "srjfw",
        "QUOTE_DT3": "xwyud",
        "ASKYRHIDAT": "zisrg",
        "ASKYRLODAT": "znnwo",
        "BIDYRHIDAT": "iiwfx",
        "BIDYRLODAT": "lgarl",
        "ASIABAC_DT": "lkqoq",
        "EUBAC_DT": "xwqro",
        "USBAC_DT": "hdtge",
        "HST_NUMBID": 18,
        "ASK_FWDOR": null,
        "BID_FWDOR": null,
        "AMERCL_ASK": 0.7,
        "AMERCL_BID": 0.23,
        "AMERHI_ASK": 0.34,
        "AMERHI_BID": 0.98,
        "AMERLO_ASK": 0.11,
        "AMERLO_BID": 0.76,
        "AMEROP_ASK": 0.51,
        "AMEROP_BID": 0.59,
        "ASIACL_ASK": 0.71,
        "ASIACL_BID": 0.31,
        "ASIAHI_ASK": 0.14,
        "ASIAHI_BID": 0.0,
        "ASIALO_ASK": 0.51,
        "ASIALO_BID": 0.11,
        "ASIAOP_ASK": 0.96,
        "ASIAOP_BID": 0.79,
        "BIDPCTCHNG": 0.99,
        "EURCL_ASK": 0.07,
        "EURCL_BID": 0.7,
        "EURHI_ASK": 0.47,
        "EURHI_BID": 0.47,
        "EURLO_ASK": 0.13,
        "EURLO_BID": 0.19,
        "EUROP_ASK": 0.41,
        "EUROP_BID": 0.36,
        "HST_HIMID": 0.35,
        "HST_LOMID": 0.26,
        "HST_OPNASK": 0.2,
        "HST_OPNBID": 0.78,
        "YRASKHIGH": 0.54,
        "YRASKLOW": 0.54,
        "ASIA_BNC": 0.53,
        "EURO_BNC": 0.9,
        "MTH_ASK_LO": 0.56,
        "MTH_BID_HI": 0.43,
        "US_BNC": 0.43,
        "WK_ASK_LO": 0.03,
        "WK_BID_HI": 0.47,
        "BID_HOURLY": 0.44,
        "RCS_AS_CL2": "jmoip",
        "MTH_ALO_DT": "vnhlr",
        "MTH_BHI_DT": "kejoc",
        "WK_ALO_DT": "ialhu",
        "WK_BHI_DT": "dyzax",
        "FXMM_TYPE": "rnxpd",
        "ASIA_AH_MS": "rfgzi",
        "ASIA_AL_MS": "zqjft",
        "ASIA_AO_MS": "ckdnb",
        "ASIA_BH_MS": "fcwig",
        "ASIA_BL_MS": "ldepq",
        "ASIA_BO_MS": "xazgq",
        "EURO_AH_MS": "nxbwo",
        "EURO_AL_MS": "xdnfj",
        "EURO_AO_MS": "eqoxc",
        "EURO_BH_MS": "ndesi",
        "EURO_BL_MS": "xawgf",
        "EURO_BO_MS": "zmauk",
        "US_AH_MS": "fbuzg",
        "US_AL_MS": "lixol",
        "US_AO_MS": "obwnt",
        "US_BH_MS": "toqww",
        "US_BL_MS": "qdozo",
        "US_BO_MS": "wbbxw",
        "OPN_BID_MS": "nlxtf",
        "ASKHI1_MS": "dnpxc",
        "ASKHI2_MS": "qlfwc",
        "ASKHI3_MS": "sjted",
        "ASKHI4_MS": "imikt",
        "ASKHI5_MS": "pnojx",
        "ASKLO1_MS": "flkth",
        "ASKLO2_MS": "nofky",
        "ASKLO3_MS": "lpotw",
        "ASKLO4_MS": "xlteg",
        "ASKLO5_MS": "efrsp",
        "BIDHI1_MS": "xvtda",
        "BIDHI2_MS": "xsnba",
        "BIDHI3_MS": "ckwcu",
        "BIDHI4_MS": "tjihv",
        "BIDHI5_MS": "pkdmr",
        "BIDLO1_MS": "lsocn",
        "BIDLO2_MS": "bybgd",
        "BIDLO3_MS": "jnkiz",
        "BIDLO4_MS": "bzwme",
        "BIDLO5_MS": "yauea",
        "MIDHI1_MS": "uafnw",
        "MIDLO1_MS": "hzxxu",
        "BID_HR_MS": "sgwjp"
    },
    {
        "PROD_PERM": 58,
        "RDNDISPLAY": 64,
        "DSPLY_NAME": "ksxuh",
        "TIMACT": "eehlx",
        "NETCHNG_1": 0.85,
        "HIGH_1": 0.66,
        "LOW_1": 0.41,
        "CURRENCY": "bhuhq",
        "ACTIV_DATE": "znglg",
        "OPEN_PRC": 0.51,
        "HST_CLOSE": 0.36,
        "BID": 0.66,
        "BID_1": 0.58,
        "BID_2": 0.42,
        "ASK": 0.1,
        "ASK_1": 0.36,
        "ASK_2": 0.5,
        "ACVOL_1": 60,
        "TRD_UNITS": "gslvx",
        "PCTCHNG": 0.17,
        "OPEN_BID": 0.61,
        "OPEN_ASK": 0.31,
        "CLOSE_BID": 0.48,
        "CLOSE_ASK": 0.85,
        "NUM_MOVES": 30,
        "OFFCL_CODE": "rswhh",
        "HSTCLSDATE": "kttqx",
        "YRHIGH": 0.49,
        "YRLOW": 0.91,
        "BCKGRNDPAG": "yjwsg",
        "BID_NET_CH": 0.9,
        "BID_TICK_1": "whlge",
        "MID_PRICE": 0.74,
        "MID_NET_CH": 0.12,
        "MID_CLOSE": 0.81,
        "HIGHTP_1": "ydbfk",
        "LOWTP_1": "urdxr",
        "BID_HIGH_1": 0.98,
        "BID_LOW_1": 0.04,
        "YRBIDHIGH": 0.19,
        "YRBIDLOW": 0.22,
        "HST_CLSBID": 0.73,
        "HSTCLBDDAT": "foamw",
        "NUM_BIDS": 28,
        "RECORDTYPE": 88,
        "ACT_TP_1": "jorww",
        "ACT_TP_2": "nevyo",
        "ACT_TP_3": "gjimj",
        "SEC_ACT_1": 0.17,
        "SEC_ACT_2": 0.26,
        "SEC_ACT_3": 0.61,
        "SC_ACT_TP1": "epkbs",
        "SC_ACT_TP2": "txapr",
        "SC_ACT_TP3": "botrf",
        "OPEN_TIME": "jufrt",
        "HIGH_TIME": "giewf",
        "LOW_TIME": "pebya",
        "YRHIGHDAT": "akqjk",
        "YRLOWDAT": "bvwbc",
        "IRGPRC": 0.94,
        "TIMCOR": "omvol",
        "PRIMACT_1": 0.72,
        "PRIMACT_2": 0.45,
        "PRIMACT_3": 0.68,
        "BASE_CCY": "ipqef",
        "BCAST_REF": "jgmkj",
        "CROSS_SC": "mgsgl",
        "DLG_CODE1": "tlrjn",
        "DLG_CODE2": "euwxp",
        "DLG_CODE3": "sceum",
        "CTBTR_1": "bafxy",
        "CTBTR_2": "mdsxr",
        "CTBTR_3": "xjdrp",
        "CTB_LOC1": "xpikx",
        "CTB_LOC2": "jqcri",
        "CTB_LOC3": "tfaha",
        "CTB_PAGE1": "uctmz",
        "CTB_PAGE2": "mftaa",
        "CTB_PAGE3": "gjpdc",
        "VALUE_DT1": "hdqkm",
        "VALUE_DT2": "fvbej",
        "VALUE_DT3": "vndwa",
        "SEC_HIGH": 0.54,
        "SEC_HI_TP": "rfbes",
        "SEC_LOW": 0.01,
        "SEC_LO_TP": "bvfdq",
        "OPEN_TYPE": "qcztv",
        "CLOSE_TYPE": "uenuy",
        "BKGD_REF": "xnewm",
        "GEN_TEXT16": "ojfsu",
        "GEN_VAL3": 0.54,
        "GEN_VAL4": 0.48,
        "GV1_TEXT": "cpzgg",
        "GV2_TEXT": "amigo",
        "GV4_TEXT": "hqnbm",
        "VALUE_TS1": "dswbc",
        "VALUE_TS2": "hbtyp",
        "VALUE_TS3": "zrajb",
        "QUOTIM": "nsogg",
        "GEN_VAL5": 0.6,
        "GEN_VAL6": 0.37,
        "GEN_VAL7": 0.55,
        "GEN_VAL8": 0.29,
        "GEN_VAL9": 0.34,
        "GEN_VAL10": 0.16,
        "GV5_TEXT": "vndnl",
        "GV6_TEXT": "rfnsx",
        "GV7_TEXT": "kyawa",
        "GV8_TEXT": "maxby",
        "GV9_TEXT": "enklj",
        "GV10_TEXT": "xhkym",
        "GN_TXT16_2": "jixuf",
        "GV1_TIME": "offjg",
        "PREF_DISP": 36,
        "GN_TXT24_1": "nnnbh",
        "DSO_ID": 3,
        "RDN_EXCHD2": "dfnng",
        "PREV_DISP": 100,
        "ASIA_CL_DT": "vfkct",
        "ASIA_CLOSE": 0.26,
        "ASIA_HI_TM": "rovnc",
        "ASIA_HIGH": 0.97,
        "ASIA_LOW": 0.25,
        "ASIA_LW_TM": "epvns",
        "ASIA_NETCH": 0.41,
        "ASIA_OP_TM": "ncudu",
        "ASIA_OPEN": 0.87,
        "EURO_CL_DT": "bfuix",
        "EURO_CLOSE": 0.98,
        "EURO_HI_TM": "bkdre",
        "EURO_HIGH": 0.28,
        "EURO_LOW": 0.68,
        "EURO_LW_TM": "fpigc",
        "EURO_NETCH": 0.69,
        "EURO_OP_TM": "xpovm",
        "EURO_OPEN": 0.76,
        "US_CL_DT": "upmph",
        "US_CLOSE": 0.75,
        "US_HI_TM": "caraf",
        "US_HIGH": 0.37,
        "US_LOW": 0.99,
        "US_LW_TM": "vfuxs",
        "US_NETCH": 0.81,
        "US_OP_TM": "kulus",
        "US_OPEN": 0.91,
        "ASK_SPREAD": 0.56,
        "BID_SPREAD": 0.48,
        "MID_SPREAD": 0.38,
        "MONTH_HIGH": 0.71,
        "MONTH_LOW": 0.82,
        "PCTCHG_3M": 0.54,
        "PCTCHG_6M": 0.59,
        "PCTCHG_MTD": 0.25,
        "PCTCHG_YTD": 0.11,
        "QUOTE_DATE": "setzi",
        "WEEK_HIGH": 0.15,
        "WEEK_LOW": 0.02,
        "ASK_HIGH_1": 0.03,
        "ASK_HI_TME": "vvhdn",
        "ASK_LOW_1": 0.26,
        "ASK_LO_TME": "siojm",
        "BID_ASK_DT": "dcgxj",
        "HIGH_2": 0.06,
        "HIGH_3": 0.17,
        "HIGH_4": 0.13,
        "HIGH_5": 0.24,
        "HIGH_TIME2": "jfctq",
        "HIGH_TIME3": "okzfu",
        "HIGH_TIME4": "ysqyt",
        "HIGH_TIME5": "pguqv",
        "LOW_2": 0.2,
        "LOW_3": 0.0,
        "LOW_4": 0.99,
        "LOW_5": 0.33,
        "LOW_TIME2": "sjmfq",
        "LOW_TIME3": "ztdnn",
        "LOW_TIME4": "uoycn",
        "LOW_TIME5": "xiruz",
        "SCALING": "cnucq",
        "START_DT": "oitvm",
        "WKHI_DT": "wwghe",
        "WKLO_DT": "gucun",
        "MTHHI_DT": "sckqh",
        "MTHLO_DT": "tnpcb",
        "QUOTIM_MS": 35,
        "MID_HIGH": 0.9,
        "MID_LOW": 0.71,
        "MID_HTIM": "iwhog",
        "MID_LTIM": "uyjtu",
        "MID_OPEN": 0.63,
        "CONTEXT_ID": 27,
        "BID_HIGH_2": 0.11,
        "BID_HIGH_3": 0.53,
        "BID_HIGH_4": 0.11,
        "BID_HIGH_5": 0.6,
        "BID_LOW_2": 0.76,
        "BID_LOW_3": 0.19,
        "BID_LOW_4": 0.48,
        "BID_LOW_5": 0.71,
        "ASK_HIGH_2": 0.07,
        "ASK_HIGH_3": 0.83,
        "ASK_HIGH_4": 0.06,
        "ASK_HIGH_5": 0.21,
        "ASK_LOW_2": 0.15,
        "ASK_LOW_3": 0.37,
        "ASK_LOW_4": 0.36,
        "ASK_LOW_5": 0.57,
        "PRV_BID_H": 0.82,
        "PRV_ASK_H": 0.8,
        "PRV_BID_L": 0.92,
        "PRV_ASK_L": 0.98,
        "DDS_DSO_ID": 92,
        "BR_LINK1": null,
        "BR_LINK2": null,
        "BR_LINK3": null,
        "SPS_SP_RIC": "vmdvo",
        "QUOTIM_2": "vfxvn",
        "QUOTIM_3": "tgqwc",
        "QUOTE_DT2": "ktfqc",
        "QUOTE_DT3": "jlzwt",
        "ASKYRHIDAT": "rpmzd",
        "ASKYRLODAT": "jfrcl",
        "BIDYRHIDAT": "bevit",
        "BIDYRLODAT": "dqrko",
        "ASIABAC_DT": "bifyv",
        "EUBAC_DT": "fqpxu",
        "USBAC_DT": "illyd",
        "HST_NUMBID": 16,
        "ASK_FWDOR": null,
        "BID_FWDOR": null,
        "AMERCL_ASK": 0.97,
        "AMERCL_BID": 0.89,
        "AMERHI_ASK": 0.88,
        "AMERHI_BID": 0.11,
        "AMERLO_ASK": 0.58,
        "AMERLO_BID": 0.77,
        "AMEROP_ASK": 0.64,
        "AMEROP_BID": 0.77,
        "ASIACL_ASK": 0.38,
        "ASIACL_BID": 0.4,
        "ASIAHI_ASK": 0.34,
        "ASIAHI_BID": 0.88,
        "ASIALO_ASK": 0.06,
        "ASIALO_BID": 0.68,
        "ASIAOP_ASK": 0.85,
        "ASIAOP_BID": 0.82,
        "BIDPCTCHNG": 0.83,
        "EURCL_ASK": 0.02,
        "EURCL_BID": 0.0,
        "EURHI_ASK": 0.55,
        "EURHI_BID": 0.52,
        "EURLO_ASK": 0.08,
        "EURLO_BID": 0.54,
        "EUROP_ASK": 0.72,
        "EUROP_BID": 0.57,
        "HST_HIMID": 0.54,
        "HST_LOMID": 0.44,
        "HST_OPNASK": 0.89,
        "HST_OPNBID": 0.02,
        "YRASKHIGH": 0.94,
        "YRASKLOW": 0.09,
        "ASIA_BNC": 0.92,
        "EURO_BNC": 0.58,
        "MTH_ASK_LO": 0.6,
        "MTH_BID_HI": 0.79,
        "US_BNC": 0.41,
        "WK_ASK_LO": 0.85,
        "WK_BID_HI": 0.85,
        "BID_HOURLY": 0.34,
        "RCS_AS_CL2": "hbsdb",
        "MTH_ALO_DT": "filkb",
        "MTH_BHI_DT": "avzmv",
        "WK_ALO_DT": "ervub",
        "WK_BHI_DT": "mxwoa",
        "FXMM_TYPE": "qbyst",
        "ASIA_AH_MS": "hwhip",
        "ASIA_AL_MS": "jkznq",
        "ASIA_AO_MS": "rhfto",
        "ASIA_BH_MS": "iumwn",
        "ASIA_BL_MS": "qreac",
        "ASIA_BO_MS": "hdfeq",
        "EURO_AH_MS": "fdwou",
        "EURO_AL_MS": "gjprs",
        "EURO_AO_MS": "jfvpa",
        "EURO_BH_MS": "oyppm",
        "EURO_BL_MS": "unkga",
        "EURO_BO_MS": "ymuje",
        "US_AH_MS": "gwric",
        "US_AL_MS": "dptxp",
        "US_AO_MS": "ugqkr",
        "US_BH_MS": "pctjo",
        "US_BL_MS": "mivjo",
        "US_BO_MS": "bpaqt",
        "OPN_BID_MS": "nmigj",
        "ASKHI1_MS": "arvsj",
        "ASKHI2_MS": "dclfx",
        "ASKHI3_MS": "bnqzg",
        "ASKHI4_MS": "lcgyu",
        "ASKHI5_MS": "bqhgb",
        "ASKLO1_MS": "ykpez",
        "ASKLO2_MS": "yjuoc",
        "ASKLO3_MS": "hwctb",
        "ASKLO4_MS": "ytwqi",
        "ASKLO5_MS": "nlajy",
        "BIDHI1_MS": "stlaj",
        "BIDHI2_MS": "lwcmk",
        "BIDHI3_MS": "thbrt",
        "BIDHI4_MS": "kuxug",
        "BIDHI5_MS": "aqcxy",
        "BIDLO1_MS": "hpjif",
        "BIDLO2_MS": "qabmy",
        "BIDLO3_MS": "tjxgt",
        "BIDLO4_MS": "ujehr",
        "BIDLO5_MS": "nnzyq",
        "MIDHI1_MS": "lcdou",
        "MIDLO1_MS": "csmrm",
        "BID_HR_MS": "qronp"
    },
    {
        "PROD_PERM": 96,
        "RDNDISPLAY": 77,
        "DSPLY_NAME": "cdyou",
        "TIMACT": "ichtp",
        "NETCHNG_1": 0.8,
        "HIGH_1": 0.99,
        "LOW_1": 0.78,
        "CURRENCY": "ewacn",
        "ACTIV_DATE": "ogiqi",
        "OPEN_PRC": 0.43,
        "HST_CLOSE": 0.85,
        "BID": 0.56,
        "BID_1": 0.19,
        "BID_2": 0.49,
        "ASK": 0.68,
        "ASK_1": 0.57,
        "ASK_2": 0.01,
        "ACVOL_1": 12,
        "TRD_UNITS": "noldw",
        "PCTCHNG": 0.98,
        "OPEN_BID": 0.12,
        "OPEN_ASK": 0.34,
        "CLOSE_BID": 0.91,
        "CLOSE_ASK": 0.34,
        "NUM_MOVES": 59,
        "OFFCL_CODE": "xeoaj",
        "HSTCLSDATE": "vxvih",
        "YRHIGH": 0.38,
        "YRLOW": 0.86,
        "BCKGRNDPAG": "bxhzy",
        "BID_NET_CH": 0.0,
        "BID_TICK_1": "cbeix",
        "MID_PRICE": 0.95,
        "MID_NET_CH": 0.59,
        "MID_CLOSE": 0.54,
        "HIGHTP_1": "mlwsl",
        "LOWTP_1": "nogqr",
        "BID_HIGH_1": 0.25,
        "BID_LOW_1": 0.15,
        "YRBIDHIGH": 0.19,
        "YRBIDLOW": 0.43,
        "HST_CLSBID": 0.21,
        "HSTCLBDDAT": "ushbv",
        "NUM_BIDS": 72,
        "RECORDTYPE": 50,
        "ACT_TP_1": "algyp",
        "ACT_TP_2": "voyhh",
        "ACT_TP_3": "omivf",
        "SEC_ACT_1": 0.94,
        "SEC_ACT_2": 0.67,
        "SEC_ACT_3": 0.57,
        "SC_ACT_TP1": "dkrfq",
        "SC_ACT_TP2": "mgsuh",
        "SC_ACT_TP3": "ctddb",
        "OPEN_TIME": "ofkac",
        "HIGH_TIME": "kaavp",
        "LOW_TIME": "wjhxz",
        "YRHIGHDAT": "zsdsh",
        "YRLOWDAT": "lnyue",
        "IRGPRC": 0.1,
        "TIMCOR": "szwzq",
        "PRIMACT_1": 0.57,
        "PRIMACT_2": 0.07,
        "PRIMACT_3": 0.47,
        "BASE_CCY": "rruvv",
        "BCAST_REF": "xsxhd",
        "CROSS_SC": "gxoqg",
        "DLG_CODE1": "lfeft",
        "DLG_CODE2": "yqhbe",
        "DLG_CODE3": "ihxtb",
        "CTBTR_1": "xtjyu",
        "CTBTR_2": "psooh",
        "CTBTR_3": "ysppa",
        "CTB_LOC1": "fisgw",
        "CTB_LOC2": "sghtd",
        "CTB_LOC3": "mnepf",
        "CTB_PAGE1": "lzups",
        "CTB_PAGE2": "rhwjv",
        "CTB_PAGE3": "bsgqs",
        "VALUE_DT1": "wylft",
        "VALUE_DT2": "ofzyh",
        "VALUE_DT3": "mloof",
        "SEC_HIGH": 0.33,
        "SEC_HI_TP": "tdhcq",
        "SEC_LOW": 0.34,
        "SEC_LO_TP": "plxyk",
        "OPEN_TYPE": "xuhbf",
        "CLOSE_TYPE": "bpwhd",
        "BKGD_REF": "mgmwh",
        "GEN_TEXT16": "siunx",
        "GEN_VAL3": 0.2,
        "GEN_VAL4": 0.88,
        "GV1_TEXT": "fgnvr",
        "GV2_TEXT": "fzgax",
        "GV4_TEXT": "omedn",
        "VALUE_TS1": "fplkb",
        "VALUE_TS2": "bnpwi",
        "VALUE_TS3": "pdfqn",
        "QUOTIM": "simfy",
        "GEN_VAL5": 0.26,
        "GEN_VAL6": 0.71,
        "GEN_VAL7": 0.91,
        "GEN_VAL8": 0.54,
        "GEN_VAL9": 0.65,
        "GEN_VAL10": 0.72,
        "GV5_TEXT": "lonks",
        "GV6_TEXT": "phvvw",
        "GV7_TEXT": "akssd",
        "GV8_TEXT": "vzlze",
        "GV9_TEXT": "irphf",
        "GV10_TEXT": "ovoxx",
        "GN_TXT16_2": "wxzaq",
        "GV1_TIME": "vxqkq",
        "PREF_DISP": 42,
        "GN_TXT24_1": "czufv",
        "DSO_ID": 45,
        "RDN_EXCHD2": "qphhe",
        "PREV_DISP": 86,
        "ASIA_CL_DT": "nyvfk",
        "ASIA_CLOSE": 0.44,
        "ASIA_HI_TM": "euzgu",
        "ASIA_HIGH": 0.88,
        "ASIA_LOW": 0.56,
        "ASIA_LW_TM": "mnohh",
        "ASIA_NETCH": 0.69,
        "ASIA_OP_TM": "bnbgb",
        "ASIA_OPEN": 0.64,
        "EURO_CL_DT": "vitoy",
        "EURO_CLOSE": 0.37,
        "EURO_HI_TM": "zypyp",
        "EURO_HIGH": 0.02,
        "EURO_LOW": 0.54,
        "EURO_LW_TM": "nalhp",
        "EURO_NETCH": 0.99,
        "EURO_OP_TM": "esfss",
        "EURO_OPEN": 0.96,
        "US_CL_DT": "gadyz",
        "US_CLOSE": 0.26,
        "US_HI_TM": "tccuv",
        "US_HIGH": 0.63,
        "US_LOW": 0.64,
        "US_LW_TM": "atztt",
        "US_NETCH": 0.58,
        "US_OP_TM": "ragib",
        "US_OPEN": 0.13,
        "ASK_SPREAD": 0.02,
        "BID_SPREAD": 0.86,
        "MID_SPREAD": 0.72,
        "MONTH_HIGH": 0.42,
        "MONTH_LOW": 0.73,
        "PCTCHG_3M": 0.17,
        "PCTCHG_6M": 0.42,
        "PCTCHG_MTD": 0.92,
        "PCTCHG_YTD": 0.8,
        "QUOTE_DATE": "pydjw",
        "WEEK_HIGH": 0.61,
        "WEEK_LOW": 0.99,
        "ASK_HIGH_1": 0.81,
        "ASK_HI_TME": "ccsmp",
        "ASK_LOW_1": 0.38,
        "ASK_LO_TME": "hdzpy",
        "BID_ASK_DT": "caxft",
        "HIGH_2": 0.91,
        "HIGH_3": 0.46,
        "HIGH_4": 0.01,
        "HIGH_5": 0.5,
        "HIGH_TIME2": "atwpo",
        "HIGH_TIME3": "cawzk",
        "HIGH_TIME4": "bjgnl",
        "HIGH_TIME5": "rgkhp",
        "LOW_2": 0.67,
        "LOW_3": 0.84,
        "LOW_4": 0.96,
        "LOW_5": 0.65,
        "LOW_TIME2": "fmfvv",
        "LOW_TIME3": "lajld",
        "LOW_TIME4": "jlpeg",
        "LOW_TIME5": "yuyhu",
        "SCALING": "dawto",
        "START_DT": "dlnns",
        "WKHI_DT": "tewtj",
        "WKLO_DT": "dtjoo",
        "MTHHI_DT": "oalgn",
        "MTHLO_DT": "umxwy",
        "QUOTIM_MS": 40,
        "MID_HIGH": 0.47,
        "MID_LOW": 0.19,
        "MID_HTIM": "qyhqo",
        "MID_LTIM": "llddb",
        "MID_OPEN": 0.98,
        "CONTEXT_ID": 41,
        "BID_HIGH_2": 0.47,
        "BID_HIGH_3": 0.21,
        "BID_HIGH_4": 0.05,
        "BID_HIGH_5": 0.86,
        "BID_LOW_2": 0.97,
        "BID_LOW_3": 0.31,
        "BID_LOW_4": 0.61,
        "BID_LOW_5": 0.2,
        "ASK_HIGH_2": 0.8,
        "ASK_HIGH_3": 0.54,
        "ASK_HIGH_4": 0.48,
        "ASK_HIGH_5": 0.74,
        "ASK_LOW_2": 0.4,
        "ASK_LOW_3": 0.73,
        "ASK_LOW_4": 0.93,
        "ASK_LOW_5": 0.3,
        "PRV_BID_H": 0.72,
        "PRV_ASK_H": 0.53,
        "PRV_BID_L": 0.12,
        "PRV_ASK_L": 0.88,
        "DDS_DSO_ID": 59,
        "BR_LINK1": null,
        "BR_LINK2": null,
        "BR_LINK3": null,
        "SPS_SP_RIC": "rpggd",
        "QUOTIM_2": "cxycv",
        "QUOTIM_3": "gjjwz",
        "QUOTE_DT2": "fwofk",
        "QUOTE_DT3": "khsli",
        "ASKYRHIDAT": "hbows",
        "ASKYRLODAT": "jjubb",
        "BIDYRHIDAT": "qktks",
        "BIDYRLODAT": "gycdn",
        "ASIABAC_DT": "fnxuy",
        "EUBAC_DT": "qkcqi",
        "USBAC_DT": "eeczx",
        "HST_NUMBID": 21,
        "ASK_FWDOR": null,
        "BID_FWDOR": null,
        "AMERCL_ASK": 0.01,
        "AMERCL_BID": 0.62,
        "AMERHI_ASK": 0.47,
        "AMERHI_BID": 0.77,
        "AMERLO_ASK": 0.02,
        "AMERLO_BID": 0.97,
        "AMEROP_ASK": 0.88,
        "AMEROP_BID": 0.85,
        "ASIACL_ASK": 0.9,
        "ASIACL_BID": 0.32,
        "ASIAHI_ASK": 0.19,
        "ASIAHI_BID": 0.27,
        "ASIALO_ASK": 0.58,
        "ASIALO_BID": 0.47,
        "ASIAOP_ASK": 0.91,
        "ASIAOP_BID": 0.97,
        "BIDPCTCHNG": 0.15,
        "EURCL_ASK": 0.41,
        "EURCL_BID": 0.86,
        "EURHI_ASK": 0.24,
        "EURHI_BID": 0.84,
        "EURLO_ASK": 0.6,
        "EURLO_BID": 0.29,
        "EUROP_ASK": 0.68,
        "EUROP_BID": 0.82,
        "HST_HIMID": 0.36,
        "HST_LOMID": 0.24,
        "HST_OPNASK": 0.87,
        "HST_OPNBID": 0.17,
        "YRASKHIGH": 0.56,
        "YRASKLOW": 0.52,
        "ASIA_BNC": 0.27,
        "EURO_BNC": 0.78,
        "MTH_ASK_LO": 0.77,
        "MTH_BID_HI": 0.22,
        "US_BNC": 0.8,
        "WK_ASK_LO": 0.62,
        "WK_BID_HI": 0.95,
        "BID_HOURLY": 0.06,
        "RCS_AS_CL2": "xaqsx",
        "MTH_ALO_DT": "xpjxf",
        "MTH_BHI_DT": "mwwdl",
        "WK_ALO_DT": "lddii",
        "WK_BHI_DT": "snlmn",
        "FXMM_TYPE": "jhnyo",
        "ASIA_AH_MS": "dymnw",
        "ASIA_AL_MS": "ozpza",
        "ASIA_AO_MS": "orqvj",
        "ASIA_BH_MS": "kczwp",
        "ASIA_BL_MS": "oigfm",
        "ASIA_BO_MS": "euupn",
        "EURO_AH_MS": "cusue",
        "EURO_AL_MS": "vmoyx",
        "EURO_AO_MS": "jgtol",
        "EURO_BH_MS": "isgns",
        "EURO_BL_MS": "egznk",
        "EURO_BO_MS": "qyxal",
        "US_AH_MS": "tptbg",
        "US_AL_MS": "oahhh",
        "US_AO_MS": "wyzic",
        "US_BH_MS": "vyqsj",
        "US_BL_MS": "jpgjq",
        "US_BO_MS": "tlrng",
        "OPN_BID_MS": "vzrjl",
        "ASKHI1_MS": "pcojy",
        "ASKHI2_MS": "edxpz",
        "ASKHI3_MS": "ggrze",
        "ASKHI4_MS": "uohlc",
        "ASKHI5_MS": "mjwqy",
        "ASKLO1_MS": "yrbdq",
        "ASKLO2_MS": "hnjel",
        "ASKLO3_MS": "mtygq",
        "ASKLO4_MS": "yewto",
        "ASKLO5_MS": "alzxa",
        "BIDHI1_MS": "dxeen",
        "BIDHI2_MS": "akosl",
        "BIDHI3_MS": "haoab",
        "BIDHI4_MS": "btlpo",
        "BIDHI5_MS": "auwzu",
        "BIDLO1_MS": "vfkta",
        "BIDLO2_MS": "pjxql",
        "BIDLO3_MS": "sprum",
        "BIDLO4_MS": "pjaga",
        "BIDLO5_MS": "fkkwp",
        "MIDHI1_MS": "uolxs",
        "MIDLO1_MS": "vsywf",
        "BID_HR_MS": "hhqic"
    },
    {
        "PROD_PERM": 52,
        "RDNDISPLAY": 38,
        "DSPLY_NAME": "oqool",
        "TIMACT": "kjovn",
        "NETCHNG_1": 0.86,
        "HIGH_1": 0.27,
        "LOW_1": 0.71,
        "CURRENCY": "nsqrw",
        "ACTIV_DATE": "bdnzh",
        "OPEN_PRC": 0.11,
        "HST_CLOSE": 0.13,
        "BID": 0.71,
        "BID_1": 0.21,
        "BID_2": 0.62,
        "ASK": 0.93,
        "ASK_1": 0.67,
        "ASK_2": 0.07,
        "ACVOL_1": 46,
        "TRD_UNITS": "iwkey",
        "PCTCHNG": 0.51,
        "OPEN_BID": 0.99,
        "OPEN_ASK": 0.11,
        "CLOSE_BID": 0.87,
        "CLOSE_ASK": 0.66,
        "NUM_MOVES": 33,
        "OFFCL_CODE": "ibhbw",
        "HSTCLSDATE": "sxych",
        "YRHIGH": 0.26,
        "YRLOW": 0.67,
        "BCKGRNDPAG": "beprv",
        "BID_NET_CH": 0.05,
        "BID_TICK_1": "dcjjn",
        "MID_PRICE": 0.27,
        "MID_NET_CH": 0.03,
        "MID_CLOSE": 0.77,
        "HIGHTP_1": "qdknf",
        "LOWTP_1": "khcfs",
        "BID_HIGH_1": 0.88,
        "BID_LOW_1": 0.44,
        "YRBIDHIGH": 0.74,
        "YRBIDLOW": 0.81,
        "HST_CLSBID": 0.39,
        "HSTCLBDDAT": "faqyv",
        "NUM_BIDS": 29,
        "RECORDTYPE": 54,
        "ACT_TP_1": "zhusf",
        "ACT_TP_2": "axzgh",
        "ACT_TP_3": "lsasw",
        "SEC_ACT_1": 0.13,
        "SEC_ACT_2": 0.01,
        "SEC_ACT_3": 0.85,
        "SC_ACT_TP1": "dpdek",
        "SC_ACT_TP2": "evcvs",
        "SC_ACT_TP3": "exalm",
        "OPEN_TIME": "medzd",
        "HIGH_TIME": "zipzw",
        "LOW_TIME": "ncpra",
        "YRHIGHDAT": "tslyx",
        "YRLOWDAT": "ielop",
        "IRGPRC": 0.11,
        "TIMCOR": "dptoh",
        "PRIMACT_1": 0.18,
        "PRIMACT_2": 0.96,
        "PRIMACT_3": 0.91,
        "BASE_CCY": "lztct",
        "BCAST_REF": "salky",
        "CROSS_SC": "ksuvc",
        "DLG_CODE1": "losaq",
        "DLG_CODE2": "pdigi",
        "DLG_CODE3": "pofus",
        "CTBTR_1": "ntqpf",
        "CTBTR_2": "zhxlh",
        "CTBTR_3": "niqqo",
        "CTB_LOC1": "mdknx",
        "CTB_LOC2": "nrxru",
        "CTB_LOC3": "mhrtw",
        "CTB_PAGE1": "enndg",
        "CTB_PAGE2": "grjag",
        "CTB_PAGE3": "bipun",
        "VALUE_DT1": "aevlj",
        "VALUE_DT2": "raimm",
        "VALUE_DT3": "hbpjf",
        "SEC_HIGH": 0.88,
        "SEC_HI_TP": "fqsoz",
        "SEC_LOW": 0.64,
        "SEC_LO_TP": "qbdwp",
        "OPEN_TYPE": "fhprb",
        "CLOSE_TYPE": "kkyre",
        "BKGD_REF": "ocoal",
        "GEN_TEXT16": "jyrnt",
        "GEN_VAL3": 0.62,
        "GEN_VAL4": 0.21,
        "GV1_TEXT": "lkyhj",
        "GV2_TEXT": "mynwb",
        "GV4_TEXT": "pcdpt",
        "VALUE_TS1": "ldfgt",
        "VALUE_TS2": "pnwtr",
        "VALUE_TS3": "stwpx",
        "QUOTIM": "retyz",
        "GEN_VAL5": 0.46,
        "GEN_VAL6": 0.06,
        "GEN_VAL7": 0.15,
        "GEN_VAL8": 0.31,
        "GEN_VAL9": 0.51,
        "GEN_VAL10": 0.9,
        "GV5_TEXT": "iokdt",
        "GV6_TEXT": "qhcas",
        "GV7_TEXT": "xkvbs",
        "GV8_TEXT": "bygzd",
        "GV9_TEXT": "xxtps",
        "GV10_TEXT": "iqxpt",
        "GN_TXT16_2": "rdnhm",
        "GV1_TIME": "xxrqs",
        "PREF_DISP": 5,
        "GN_TXT24_1": "xcawu",
        "DSO_ID": 69,
        "RDN_EXCHD2": "zjtdg",
        "PREV_DISP": 36,
        "ASIA_CL_DT": "dymtf",
        "ASIA_CLOSE": 0.36,
        "ASIA_HI_TM": "hheez",
        "ASIA_HIGH": 0.37,
        "ASIA_LOW": 0.04,
        "ASIA_LW_TM": "xytea",
        "ASIA_NETCH": 0.18,
        "ASIA_OP_TM": "lafqk",
        "ASIA_OPEN": 0.21,
        "EURO_CL_DT": "sdcpl",
        "EURO_CLOSE": 0.35,
        "EURO_HI_TM": "yfgon",
        "EURO_HIGH": 0.47,
        "EURO_LOW": 0.78,
        "EURO_LW_TM": "zbjvp",
        "EURO_NETCH": 0.06,
        "EURO_OP_TM": "gcovt",
        "EURO_OPEN": 0.71,
        "US_CL_DT": "pubyg",
        "US_CLOSE": 0.93,
        "US_HI_TM": "cpexk",
        "US_HIGH": 0.89,
        "US_LOW": 0.8,
        "US_LW_TM": "pcucd",
        "US_NETCH": 0.18,
        "US_OP_TM": "hopeo",
        "US_OPEN": 0.27,
        "ASK_SPREAD": 0.06,
        "BID_SPREAD": 0.41,
        "MID_SPREAD": 0.57,
        "MONTH_HIGH": 0.98,
        "MONTH_LOW": 0.94,
        "PCTCHG_3M": 0.61,
        "PCTCHG_6M": 0.26,
        "PCTCHG_MTD": 0.94,
        "PCTCHG_YTD": 0.42,
        "QUOTE_DATE": "qlqqk",
        "WEEK_HIGH": 0.27,
        "WEEK_LOW": 0.08,
        "ASK_HIGH_1": 0.03,
        "ASK_HI_TME": "zktxo",
        "ASK_LOW_1": 0.54,
        "ASK_LO_TME": "tnwxx",
        "BID_ASK_DT": "undun",
        "HIGH_2": 0.02,
        "HIGH_3": 0.86,
        "HIGH_4": 0.14,
        "HIGH_5": 0.86,
        "HIGH_TIME2": "ypthd",
        "HIGH_TIME3": "ncnbg",
        "HIGH_TIME4": "gofet",
        "HIGH_TIME5": "wtxfj",
        "LOW_2": 0.91,
        "LOW_3": 0.93,
        "LOW_4": 0.72,
        "LOW_5": 0.19,
        "LOW_TIME2": "luciw",
        "LOW_TIME3": "kgooo",
        "LOW_TIME4": "jkbnh",
        "LOW_TIME5": "eihtz",
        "SCALING": "jgnwi",
        "START_DT": "jqazr",
        "WKHI_DT": "tyejz",
        "WKLO_DT": "xbqsy",
        "MTHHI_DT": "fxibo",
        "MTHLO_DT": "azwmp",
        "QUOTIM_MS": 75,
        "MID_HIGH": 0.09,
        "MID_LOW": 0.27,
        "MID_HTIM": "fqwpq",
        "MID_LTIM": "rlots",
        "MID_OPEN": 0.99,
        "CONTEXT_ID": 95,
        "BID_HIGH_2": 0.64,
        "BID_HIGH_3": 0.04,
        "BID_HIGH_4": 0.37,
        "BID_HIGH_5": 0.6,
        "BID_LOW_2": 0.04,
        "BID_LOW_3": 0.05,
        "BID_LOW_4": 0.25,
        "BID_LOW_5": 0.86,
        "ASK_HIGH_2": 0.38,
        "ASK_HIGH_3": 0.54,
        "ASK_HIGH_4": 0.82,
        "ASK_HIGH_5": 0.17,
        "ASK_LOW_2": 0.55,
        "ASK_LOW_3": 0.59,
        "ASK_LOW_4": 0.13,
        "ASK_LOW_5": 0.84,
        "PRV_BID_H": 0.88,
        "PRV_ASK_H": 0.8,
        "PRV_BID_L": 0.73,
        "PRV_ASK_L": 0.62,
        "DDS_DSO_ID": 63,
        "BR_LINK1": null,
        "BR_LINK2": null,
        "BR_LINK3": null,
        "SPS_SP_RIC": "ipedu",
        "QUOTIM_2": "cveal",
        "QUOTIM_3": "wvvax",
        "QUOTE_DT2": "xizfw",
        "QUOTE_DT3": "ktlkl",
        "ASKYRHIDAT": "uovup",
        "ASKYRLODAT": "zozzu",
        "BIDYRHIDAT": "kuahi",
        "BIDYRLODAT": "ystsr",
        "ASIABAC_DT": "paxjr",
        "EUBAC_DT": "pblud",
        "USBAC_DT": "knhlx",
        "HST_NUMBID": 77,
        "ASK_FWDOR": null,
        "BID_FWDOR": null,
        "AMERCL_ASK": 0.42,
        "AMERCL_BID": 0.39,
        "AMERHI_ASK": 0.57,
        "AMERHI_BID": 0.48,
        "AMERLO_ASK": 0.77,
        "AMERLO_BID": 0.77,
        "AMEROP_ASK": 0.26,
        "AMEROP_BID": 0.14,
        "ASIACL_ASK": 0.3,
        "ASIACL_BID": 0.96,
        "ASIAHI_ASK": 0.41,
        "ASIAHI_BID": 0.89,
        "ASIALO_ASK": 0.78,
        "ASIALO_BID": 0.51,
        "ASIAOP_ASK": 0.88,
        "ASIAOP_BID": 0.77,
        "BIDPCTCHNG": 0.65,
        "EURCL_ASK": 0.04,
        "EURCL_BID": 0.01,
        "EURHI_ASK": 0.75,
        "EURHI_BID": 0.75,
        "EURLO_ASK": 0.59,
        "EURLO_BID": 0.29,
        "EUROP_ASK": 0.88,
        "EUROP_BID": 0.66,
        "HST_HIMID": 0.71,
        "HST_LOMID": 0.29,
        "HST_OPNASK": 0.71,
        "HST_OPNBID": 0.27,
        "YRASKHIGH": 0.53,
        "YRASKLOW": 0.4,
        "ASIA_BNC": 0.21,
        "EURO_BNC": 0.33,
        "MTH_ASK_LO": 0.14,
        "MTH_BID_HI": 0.08,
        "US_BNC": 0.76,
        "WK_ASK_LO": 0.21,
        "WK_BID_HI": 0.74,
        "BID_HOURLY": 0.03,
        "RCS_AS_CL2": "vbhqm",
        "MTH_ALO_DT": "rsbfs",
        "MTH_BHI_DT": "swcfu",
        "WK_ALO_DT": "koiyv",
        "WK_BHI_DT": "ljemb",
        "FXMM_TYPE": "kbsbr",
        "ASIA_AH_MS": "qrvpd",
        "ASIA_AL_MS": "eboaw",
        "ASIA_AO_MS": "fwfbl",
        "ASIA_BH_MS": "vjkjt",
        "ASIA_BL_MS": "lhmsc",
        "ASIA_BO_MS": "emzfx",
        "EURO_AH_MS": "pmcne",
        "EURO_AL_MS": "atvux",
        "EURO_AO_MS": "qxyxh",
        "EURO_BH_MS": "flwkb",
        "EURO_BL_MS": "fxscd",
        "EURO_BO_MS": "lmzvr",
        "US_AH_MS": "ghshi",
        "US_AL_MS": "dopfl",
        "US_AO_MS": "adwkw",
        "US_BH_MS": "zblzg",
        "US_BL_MS": "muevo",
        "US_BO_MS": "rwrqq",
        "OPN_BID_MS": "xkmxs",
        "ASKHI1_MS": "qraxl",
        "ASKHI2_MS": "vdnmt",
        "ASKHI3_MS": "oicou",
        "ASKHI4_MS": "nvlel",
        "ASKHI5_MS": "cyisj",
        "ASKLO1_MS": "fkipx",
        "ASKLO2_MS": "colsc",
        "ASKLO3_MS": "ytima",
        "ASKLO4_MS": "eeegc",
        "ASKLO5_MS": "agufu",
        "BIDHI1_MS": "vdkti",
        "BIDHI2_MS": "pznmq",
        "BIDHI3_MS": "ayked",
        "BIDHI4_MS": "lohjv",
        "BIDHI5_MS": "tbmed",
        "BIDLO1_MS": "vnypn",
        "BIDLO2_MS": "yjqmv",
        "BIDLO3_MS": "gdrsj",
        "BIDLO4_MS": "bbtzn",
        "BIDLO5_MS": "gqfkh",
        "MIDHI1_MS": "sfyds",
        "MIDLO1_MS": "vvhxi",
        "BID_HR_MS": "tnxqu"
    },
    {
        "PROD_PERM": 33,
        "RDNDISPLAY": 55,
        "DSPLY_NAME": "tctyp",
        "TIMACT": "olynk",
        "NETCHNG_1": 0.45,
        "HIGH_1": 0.63,
        "LOW_1": 0.5,
        "CURRENCY": "jdlja",
        "ACTIV_DATE": "pedlp",
        "OPEN_PRC": 0.08,
        "HST_CLOSE": 0.82,
        "BID": 0.33,
        "BID_1": 0.1,
        "BID_2": 0.91,
        "ASK": 0.47,
        "ASK_1": 0.11,
        "ASK_2": 0.29,
        "ACVOL_1": 53,
        "TRD_UNITS": "pvycu",
        "PCTCHNG": 0.04,
        "OPEN_BID": 0.07,
        "OPEN_ASK": 0.5,
        "CLOSE_BID": 0.34,
        "CLOSE_ASK": 0.81,
        "NUM_MOVES": 95,
        "OFFCL_CODE": "jqqbo",
        "HSTCLSDATE": "gunni",
        "YRHIGH": 0.92,
        "YRLOW": 0.52,
        "BCKGRNDPAG": "nmtby",
        "BID_NET_CH": 0.77,
        "BID_TICK_1": "vcrjy",
        "MID_PRICE": 0.7,
        "MID_NET_CH": 0.68,
        "MID_CLOSE": 0.03,
        "HIGHTP_1": "fkect",
        "LOWTP_1": "tmalf",
        "BID_HIGH_1": 0.88,
        "BID_LOW_1": 0.73,
        "YRBIDHIGH": 0.47,
        "YRBIDLOW": 0.2,
        "HST_CLSBID": 0.91,
        "HSTCLBDDAT": "hxbmn",
        "NUM_BIDS": 67,
        "RECORDTYPE": 81,
        "ACT_TP_1": "kofnv",
        "ACT_TP_2": "tqnps",
        "ACT_TP_3": "ytkdy",
        "SEC_ACT_1": 0.01,
        "SEC_ACT_2": 0.72,
        "SEC_ACT_3": 0.78,
        "SC_ACT_TP1": "twbpu",
        "SC_ACT_TP2": "bbuoc",
        "SC_ACT_TP3": "quaap",
        "OPEN_TIME": "kzufg",
        "HIGH_TIME": "nowtk",
        "LOW_TIME": "izvxz",
        "YRHIGHDAT": "nmzam",
        "YRLOWDAT": "erhsx",
        "IRGPRC": 0.68,
        "TIMCOR": "kfafg",
        "PRIMACT_1": 0.85,
        "PRIMACT_2": 0.52,
        "PRIMACT_3": 0.48,
        "BASE_CCY": "nvpwa",
        "BCAST_REF": "jpttx",
        "CROSS_SC": "tgozg",
        "DLG_CODE1": "adfvi",
        "DLG_CODE2": "smhzd",
        "DLG_CODE3": "accea",
        "CTBTR_1": "toepp",
        "CTBTR_2": "ptrmk",
        "CTBTR_3": "esimo",
        "CTB_LOC1": "qhkiy",
        "CTB_LOC2": "utuwb",
        "CTB_LOC3": "bjzzj",
        "CTB_PAGE1": "mqlao",
        "CTB_PAGE2": "xbimi",
        "CTB_PAGE3": "wmsqg",
        "VALUE_DT1": "jgwsg",
        "VALUE_DT2": "nczba",
        "VALUE_DT3": "daamq",
        "SEC_HIGH": 0.66,
        "SEC_HI_TP": "vpgmu",
        "SEC_LOW": 0.93,
        "SEC_LO_TP": "ienvh",
        "OPEN_TYPE": "jkrie",
        "CLOSE_TYPE": "lwtuh",
        "BKGD_REF": "ceolv",
        "GEN_TEXT16": "ljtdi",
        "GEN_VAL3": 0.63,
        "GEN_VAL4": 0.41,
        "GV1_TEXT": "rxzyf",
        "GV2_TEXT": "cbzzk",
        "GV4_TEXT": "kfmol",
        "VALUE_TS1": "anhel",
        "VALUE_TS2": "gzncw",
        "VALUE_TS3": "gqita",
        "QUOTIM": "nlhqu",
        "GEN_VAL5": 0.87,
        "GEN_VAL6": 0.19,
        "GEN_VAL7": 0.66,
        "GEN_VAL8": 0.65,
        "GEN_VAL9": 0.29,
        "GEN_VAL10": 0.51,
        "GV5_TEXT": "xdlyk",
        "GV6_TEXT": "yipoe",
        "GV7_TEXT": "kfgnq",
        "GV8_TEXT": "xfcht",
        "GV9_TEXT": "igbpc",
        "GV10_TEXT": "gpzmq",
        "GN_TXT16_2": "cnymy",
        "GV1_TIME": "ezgwq",
        "PREF_DISP": 22,
        "GN_TXT24_1": "ktalo",
        "DSO_ID": 23,
        "RDN_EXCHD2": "mqiaw",
        "PREV_DISP": 11,
        "ASIA_CL_DT": "zswxv",
        "ASIA_CLOSE": 0.5,
        "ASIA_HI_TM": "llwim",
        "ASIA_HIGH": 0.72,
        "ASIA_LOW": 0.12,
        "ASIA_LW_TM": "lphye",
        "ASIA_NETCH": 0.05,
        "ASIA_OP_TM": "ikrzw",
        "ASIA_OPEN": 0.7,
        "EURO_CL_DT": "yirzh",
        "EURO_CLOSE": 0.96,
        "EURO_HI_TM": "ihlpt",
        "EURO_HIGH": 0.04,
        "EURO_LOW": 0.49,
        "EURO_LW_TM": "mcply",
        "EURO_NETCH": 0.91,
        "EURO_OP_TM": "scfsm",
        "EURO_OPEN": 0.63,
        "US_CL_DT": "uwbko",
        "US_CLOSE": 0.9,
        "US_HI_TM": "cyycg",
        "US_HIGH": 0.84,
        "US_LOW": 0.09,
        "US_LW_TM": "xhznp",
        "US_NETCH": 0.72,
        "US_OP_TM": "kdrkh",
        "US_OPEN": 0.87,
        "ASK_SPREAD": 0.99,
        "BID_SPREAD": 0.17,
        "MID_SPREAD": 0.78,
        "MONTH_HIGH": 0.58,
        "MONTH_LOW": 0.19,
        "PCTCHG_3M": 0.8,
        "PCTCHG_6M": 0.3,
        "PCTCHG_MTD": 0.59,
        "PCTCHG_YTD": 0.45,
        "QUOTE_DATE": "iryjw",
        "WEEK_HIGH": 0.63,
        "WEEK_LOW": 0.19,
        "ASK_HIGH_1": 0.06,
        "ASK_HI_TME": "tnlod",
        "ASK_LOW_1": 0.78,
        "ASK_LO_TME": "ozdks",
        "BID_ASK_DT": "leezu",
        "HIGH_2": 0.77,
        "HIGH_3": 0.95,
        "HIGH_4": 0.75,
        "HIGH_5": 0.93,
        "HIGH_TIME2": "rjlnb",
        "HIGH_TIME3": "onvhc",
        "HIGH_TIME4": "spwur",
        "HIGH_TIME5": "ezezl",
        "LOW_2": 0.74,
        "LOW_3": 0.65,
        "LOW_4": 0.57,
        "LOW_5": 0.42,
        "LOW_TIME2": "xczec",
        "LOW_TIME3": "rfvzs",
        "LOW_TIME4": "ofjoh",
        "LOW_TIME5": "cyvml",
        "SCALING": "xfqij",
        "START_DT": "nbnvi",
        "WKHI_DT": "onzzn",
        "WKLO_DT": "dnjgd",
        "MTHHI_DT": "uzkgo",
        "MTHLO_DT": "kgepd",
        "QUOTIM_MS": 26,
        "MID_HIGH": 0.4,
        "MID_LOW": 0.08,
        "MID_HTIM": "xydgi",
        "MID_LTIM": "zchtt",
        "MID_OPEN": 0.31,
        "CONTEXT_ID": 79,
        "BID_HIGH_2": 0.62,
        "BID_HIGH_3": 0.87,
        "BID_HIGH_4": 0.39,
        "BID_HIGH_5": 0.99,
        "BID_LOW_2": 0.58,
        "BID_LOW_3": 0.02,
        "BID_LOW_4": 0.42,
        "BID_LOW_5": 0.45,
        "ASK_HIGH_2": 0.48,
        "ASK_HIGH_3": 0.48,
        "ASK_HIGH_4": 0.17,
        "ASK_HIGH_5": 0.97,
        "ASK_LOW_2": 0.6,
        "ASK_LOW_3": 0.02,
        "ASK_LOW_4": 0.88,
        "ASK_LOW_5": 0.34,
        "PRV_BID_H": 0.08,
        "PRV_ASK_H": 0.69,
        "PRV_BID_L": 0.78,
        "PRV_ASK_L": 0.04,
        "DDS_DSO_ID": 97,
        "BR_LINK1": null,
        "BR_LINK2": null,
        "BR_LINK3": null,
        "SPS_SP_RIC": "puhop",
        "QUOTIM_2": "gvkfw",
        "QUOTIM_3": "ixyrq",
        "QUOTE_DT2": "eihep",
        "QUOTE_DT3": "mueuk",
        "ASKYRHIDAT": "czvlt",
        "ASKYRLODAT": "dgsgi",
        "BIDYRHIDAT": "dclwa",
        "BIDYRLODAT": "cyjnz",
        "ASIABAC_DT": "eowrh",
        "EUBAC_DT": "xrpdi",
        "USBAC_DT": "rtwfh",
        "HST_NUMBID": 5,
        "ASK_FWDOR": null,
        "BID_FWDOR": null,
        "AMERCL_ASK": 0.61,
        "AMERCL_BID": 0.82,
        "AMERHI_ASK": 0.67,
        "AMERHI_BID": 0.75,
        "AMERLO_ASK": 0.85,
        "AMERLO_BID": 0.16,
        "AMEROP_ASK": 0.1,
        "AMEROP_BID": 0.23,
        "ASIACL_ASK": 0.78,
        "ASIACL_BID": 0.54,
        "ASIAHI_ASK": 0.64,
        "ASIAHI_BID": 0.08,
        "ASIALO_ASK": 0.67,
        "ASIALO_BID": 0.39,
        "ASIAOP_ASK": 0.34,
        "ASIAOP_BID": 0.61,
        "BIDPCTCHNG": 0.38,
        "EURCL_ASK": 0.85,
        "EURCL_BID": 0.9,
        "EURHI_ASK": 0.33,
        "EURHI_BID": 0.39,
        "EURLO_ASK": 0.71,
        "EURLO_BID": 0.16,
        "EUROP_ASK": 0.31,
        "EUROP_BID": 0.4,
        "HST_HIMID": 0.11,
        "HST_LOMID": 0.08,
        "HST_OPNASK": 0.04,
        "HST_OPNBID": 0.01,
        "YRASKHIGH": 0.52,
        "YRASKLOW": 0.36,
        "ASIA_BNC": 0.88,
        "EURO_BNC": 0.95,
        "MTH_ASK_LO": 0.27,
        "MTH_BID_HI": 0.81,
        "US_BNC": 0.58,
        "WK_ASK_LO": 0.88,
        "WK_BID_HI": 0.89,
        "BID_HOURLY": 0.75,
        "RCS_AS_CL2": "brjwf",
        "MTH_ALO_DT": "uuuks",
        "MTH_BHI_DT": "ozfhr",
        "WK_ALO_DT": "imqlz",
        "WK_BHI_DT": "urxtm",
        "FXMM_TYPE": "svqlx",
        "ASIA_AH_MS": "kilrj",
        "ASIA_AL_MS": "viwoy",
        "ASIA_AO_MS": "gjkon",
        "ASIA_BH_MS": "czxfj",
        "ASIA_BL_MS": "crqcx",
        "ASIA_BO_MS": "thdho",
        "EURO_AH_MS": "rwobp",
        "EURO_AL_MS": "rjzlp",
        "EURO_AO_MS": "rteio",
        "EURO_BH_MS": "kqbup",
        "EURO_BL_MS": "hwhql",
        "EURO_BO_MS": "manid",
        "US_AH_MS": "gqnxg",
        "US_AL_MS": "dniur",
        "US_AO_MS": "jdgix",
        "US_BH_MS": "nkwak",
        "US_BL_MS": "mjdan",
        "US_BO_MS": "uvmrm",
        "OPN_BID_MS": "pnosp",
        "ASKHI1_MS": "htlut",
        "ASKHI2_MS": "qywub",
        "ASKHI3_MS": "yzcyc",
        "ASKHI4_MS": "auoli",
        "ASKHI5_MS": "hyyjb",
        "ASKLO1_MS": "wmeet",
        "ASKLO2_MS": "qqafb",
        "ASKLO3_MS": "nuagc",
        "ASKLO4_MS": "ilnat",
        "ASKLO5_MS": "gmbzq",
        "BIDHI1_MS": "asndh",
        "BIDHI2_MS": "eqtev",
        "BIDHI3_MS": "xqxyg",
        "BIDHI4_MS": "zsget",
        "BIDHI5_MS": "jutst",
        "BIDLO1_MS": "sswwc",
        "BIDLO2_MS": "ptvzj",
        "BIDLO3_MS": "aobqq",
        "BIDLO4_MS": "xnthv",
        "BIDLO5_MS": "rxetj",
        "MIDHI1_MS": "izykj",
        "MIDLO1_MS": "mogeg",
        "BID_HR_MS": "jkwqt"
    },
    {
        "PROD_PERM": 86,
        "RDNDISPLAY": 30,
        "DSPLY_NAME": "tvbhv",
        "TIMACT": "dqrga",
        "NETCHNG_1": 0.06,
        "HIGH_1": 0.45,
        "LOW_1": 0.84,
        "CURRENCY": "pcafq",
        "ACTIV_DATE": "ssmct",
        "OPEN_PRC": 0.52,
        "HST_CLOSE": 0.39,
        "BID": 0.04,
        "BID_1": 0.7,
        "BID_2": 0.33,
        "ASK": 0.93,
        "ASK_1": 0.09,
        "ASK_2": 0.71,
        "ACVOL_1": 63,
        "TRD_UNITS": "ssphy",
        "PCTCHNG": 0.86,
        "OPEN_BID": 0.65,
        "OPEN_ASK": 0.53,
        "CLOSE_BID": 0.18,
        "CLOSE_ASK": 0.81,
        "NUM_MOVES": 48,
        "OFFCL_CODE": "vgydp",
        "HSTCLSDATE": "ycckq",
        "YRHIGH": 0.68,
        "YRLOW": 0.02,
        "BCKGRNDPAG": "uozzd",
        "BID_NET_CH": 0.77,
        "BID_TICK_1": "qxryp",
        "MID_PRICE": 0.8,
        "MID_NET_CH": 0.79,
        "MID_CLOSE": 0.08,
        "HIGHTP_1": "aqfua",
        "LOWTP_1": "slzil",
        "BID_HIGH_1": 0.99,
        "BID_LOW_1": 0.66,
        "YRBIDHIGH": 0.27,
        "YRBIDLOW": 0.16,
        "HST_CLSBID": 0.52,
        "HSTCLBDDAT": "pygng",
        "NUM_BIDS": 31,
        "RECORDTYPE": 99,
        "ACT_TP_1": "nwyzv",
        "ACT_TP_2": "xyges",
        "ACT_TP_3": "svxmo",
        "SEC_ACT_1": 0.95,
        "SEC_ACT_2": 0.32,
        "SEC_ACT_3": 0.03,
        "SC_ACT_TP1": "hhbtj",
        "SC_ACT_TP2": "cfnpl",
        "SC_ACT_TP3": "xuasd",
        "OPEN_TIME": "imtxp",
        "HIGH_TIME": "safky",
        "LOW_TIME": "kmzdk",
        "YRHIGHDAT": "ieiis",
        "YRLOWDAT": "ootbl",
        "IRGPRC": 0.1,
        "TIMCOR": "kloyl",
        "PRIMACT_1": 0.25,
        "PRIMACT_2": 0.33,
        "PRIMACT_3": 0.77,
        "BASE_CCY": "tqlke",
        "BCAST_REF": "vbkwg",
        "CROSS_SC": "ediyk",
        "DLG_CODE1": "nkgbt",
        "DLG_CODE2": "ajdjp",
        "DLG_CODE3": "cmreq",
        "CTBTR_1": "adriu",
        "CTBTR_2": "jotgt",
        "CTBTR_3": "xnjzf",
        "CTB_LOC1": "paoxf",
        "CTB_LOC2": "lcbbl",
        "CTB_LOC3": "hmkka",
        "CTB_PAGE1": "cppck",
        "CTB_PAGE2": "mjpdi",
        "CTB_PAGE3": "beugo",
        "VALUE_DT1": "zxvsn",
        "VALUE_DT2": "usdmo",
        "VALUE_DT3": "egahb",
        "SEC_HIGH": 0.77,
        "SEC_HI_TP": "txbyz",
        "SEC_LOW": 0.04,
        "SEC_LO_TP": "afqin",
        "OPEN_TYPE": "bmzst",
        "CLOSE_TYPE": "klycv",
        "BKGD_REF": "cenjr",
        "GEN_TEXT16": "ceagk",
        "GEN_VAL3": 0.05,
        "GEN_VAL4": 0.5,
        "GV1_TEXT": "rwuge",
        "GV2_TEXT": "syfba",
        "GV4_TEXT": "tkjfb",
        "VALUE_TS1": "zcrwy",
        "VALUE_TS2": "mcbjm",
        "VALUE_TS3": "xyiqt",
        "QUOTIM": "nccyu",
        "GEN_VAL5": 0.84,
        "GEN_VAL6": 0.56,
        "GEN_VAL7": 0.46,
        "GEN_VAL8": 0.79,
        "GEN_VAL9": 0.01,
        "GEN_VAL10": 0.73,
        "GV5_TEXT": "mfpsi",
        "GV6_TEXT": "vysnl",
        "GV7_TEXT": "diwpr",
        "GV8_TEXT": "gtllt",
        "GV9_TEXT": "grjrz",
        "GV10_TEXT": "uskri",
        "GN_TXT16_2": "ykbyw",
        "GV1_TIME": "uxpdx",
        "PREF_DISP": 85,
        "GN_TXT24_1": "rbqgt",
        "DSO_ID": 6,
        "RDN_EXCHD2": "rhjfn",
        "PREV_DISP": 1,
        "ASIA_CL_DT": "rznql",
        "ASIA_CLOSE": 0.01,
        "ASIA_HI_TM": "iujev",
        "ASIA_HIGH": 0.62,
        "ASIA_LOW": 0.89,
        "ASIA_LW_TM": "gcqzp",
        "ASIA_NETCH": 0.98,
        "ASIA_OP_TM": "kwloy",
        "ASIA_OPEN": 0.21,
        "EURO_CL_DT": "rnltl",
        "EURO_CLOSE": 0.27,
        "EURO_HI_TM": "exldj",
        "EURO_HIGH": 0.89,
        "EURO_LOW": 0.92,
        "EURO_LW_TM": "ofkws",
        "EURO_NETCH": 0.36,
        "EURO_OP_TM": "gnkqf",
        "EURO_OPEN": 0.25,
        "US_CL_DT": "lmnwz",
        "US_CLOSE": 0.39,
        "US_HI_TM": "vgybd",
        "US_HIGH": 0.31,
        "US_LOW": 0.9,
        "US_LW_TM": "wgcat",
        "US_NETCH": 0.99,
        "US_OP_TM": "ddxju",
        "US_OPEN": 0.62,
        "ASK_SPREAD": 0.81,
        "BID_SPREAD": 0.74,
        "MID_SPREAD": 0.82,
        "MONTH_HIGH": 0.05,
        "MONTH_LOW": 0.83,
        "PCTCHG_3M": 0.22,
        "PCTCHG_6M": 0.36,
        "PCTCHG_MTD": 0.61,
        "PCTCHG_YTD": 0.96,
        "QUOTE_DATE": "wrxhw",
        "WEEK_HIGH": 0.67,
        "WEEK_LOW": 0.84,
        "ASK_HIGH_1": 0.59,
        "ASK_HI_TME": "jxbmk",
        "ASK_LOW_1": 0.44,
        "ASK_LO_TME": "jwblc",
        "BID_ASK_DT": "ikwxp",
        "HIGH_2": 0.55,
        "HIGH_3": 0.74,
        "HIGH_4": 0.19,
        "HIGH_5": 0.03,
        "HIGH_TIME2": "gpwwd",
        "HIGH_TIME3": "hjhpe",
        "HIGH_TIME4": "zbcdq",
        "HIGH_TIME5": "xyqmi",
        "LOW_2": 0.1,
        "LOW_3": 0.43,
        "LOW_4": 0.0,
        "LOW_5": 0.45,
        "LOW_TIME2": "nifya",
        "LOW_TIME3": "zmwcr",
        "LOW_TIME4": "lcodn",
        "LOW_TIME5": "mdmkc",
        "SCALING": "sxtdm",
        "START_DT": "qszzd",
        "WKHI_DT": "qnfrx",
        "WKLO_DT": "nskrj",
        "MTHHI_DT": "kaogw",
        "MTHLO_DT": "tngli",
        "QUOTIM_MS": 41,
        "MID_HIGH": 0.07,
        "MID_LOW": 0.56,
        "MID_HTIM": "bevue",
        "MID_LTIM": "aznsd",
        "MID_OPEN": 0.62,
        "CONTEXT_ID": 8,
        "BID_HIGH_2": 0.61,
        "BID_HIGH_3": 0.83,
        "BID_HIGH_4": 0.91,
        "BID_HIGH_5": 0.29,
        "BID_LOW_2": 0.37,
        "BID_LOW_3": 0.95,
        "BID_LOW_4": 0.97,
        "BID_LOW_5": 0.38,
        "ASK_HIGH_2": 0.57,
        "ASK_HIGH_3": 0.67,
        "ASK_HIGH_4": 0.33,
        "ASK_HIGH_5": 0.83,
        "ASK_LOW_2": 0.96,
        "ASK_LOW_3": 0.59,
        "ASK_LOW_4": 0.92,
        "ASK_LOW_5": 0.69,
        "PRV_BID_H": 0.93,
        "PRV_ASK_H": 0.74,
        "PRV_BID_L": 0.1,
        "PRV_ASK_L": 0.99,
        "DDS_DSO_ID": 90,
        "BR_LINK1": null,
        "BR_LINK2": null,
        "BR_LINK3": null,
        "SPS_SP_RIC": "eazgm",
        "QUOTIM_2": "inlnh",
        "QUOTIM_3": "afgrd",
        "QUOTE_DT2": "sbkmv",
        "QUOTE_DT3": "ppynh",
        "ASKYRHIDAT": "bqtif",
        "ASKYRLODAT": "iceir",
        "BIDYRHIDAT": "fkzre",
        "BIDYRLODAT": "scjvx",
        "ASIABAC_DT": "cedly",
        "EUBAC_DT": "nwhve",
        "USBAC_DT": "hlwfq",
        "HST_NUMBID": 1,
        "ASK_FWDOR": null,
        "BID_FWDOR": null,
        "AMERCL_ASK": 0.7,
        "AMERCL_BID": 0.7,
        "AMERHI_ASK": 0.22,
        "AMERHI_BID": 0.86,
        "AMERLO_ASK": 0.28,
        "AMERLO_BID": 0.81,
        "AMEROP_ASK": 0.13,
        "AMEROP_BID": 0.91,
        "ASIACL_ASK": 0.87,
        "ASIACL_BID": 0.57,
        "ASIAHI_ASK": 0.42,
        "ASIAHI_BID": 0.35,
        "ASIALO_ASK": 0.35,
        "ASIALO_BID": 0.97,
        "ASIAOP_ASK": 0.84,
        "ASIAOP_BID": 0.34,
        "BIDPCTCHNG": 0.03,
        "EURCL_ASK": 0.69,
        "EURCL_BID": 0.78,
        "EURHI_ASK": 0.25,
        "EURHI_BID": 0.53,
        "EURLO_ASK": 0.2,
        "EURLO_BID": 0.2,
        "EUROP_ASK": 0.39,
        "EUROP_BID": 0.99,
        "HST_HIMID": 0.03,
        "HST_LOMID": 0.36,
        "HST_OPNASK": 0.89,
        "HST_OPNBID": 0.15,
        "YRASKHIGH": 0.35,
        "YRASKLOW": 0.95,
        "ASIA_BNC": 0.93,
        "EURO_BNC": 0.72,
        "MTH_ASK_LO": 0.21,
        "MTH_BID_HI": 0.42,
        "US_BNC": 0.74,
        "WK_ASK_LO": 0.66,
        "WK_BID_HI": 0.56,
        "BID_HOURLY": 0.18,
        "RCS_AS_CL2": "ryrcb",
        "MTH_ALO_DT": "xttoj",
        "MTH_BHI_DT": "ahuvr",
        "WK_ALO_DT": "xlriq",
        "WK_BHI_DT": "uyzdj",
        "FXMM_TYPE": "nmqnw",
        "ASIA_AH_MS": "jlhuw",
        "ASIA_AL_MS": "bkkto",
        "ASIA_AO_MS": "xwgzt",
        "ASIA_BH_MS": "zomee",
        "ASIA_BL_MS": "ptbkl",
        "ASIA_BO_MS": "gqvso",
        "EURO_AH_MS": "ajvox",
        "EURO_AL_MS": "sbirs",
        "EURO_AO_MS": "jbdng",
        "EURO_BH_MS": "oyutr",
        "EURO_BL_MS": "wdycs",
        "EURO_BO_MS": "fiaby",
        "US_AH_MS": "hphjo",
        "US_AL_MS": "wdbyp",
        "US_AO_MS": "keedp",
        "US_BH_MS": "nmild",
        "US_BL_MS": "llqsh",
        "US_BO_MS": "nwftf",
        "OPN_BID_MS": "nxqkp",
        "ASKHI1_MS": "dswsl",
        "ASKHI2_MS": "eqlbh",
        "ASKHI3_MS": "zcllq",
        "ASKHI4_MS": "drfim",
        "ASKHI5_MS": "qwbll",
        "ASKLO1_MS": "udixo",
        "ASKLO2_MS": "tijcs",
        "ASKLO3_MS": "yripx",
        "ASKLO4_MS": "sulnu",
        "ASKLO5_MS": "qbfjx",
        "BIDHI1_MS": "lmqhj",
        "BIDHI2_MS": "xqazb",
        "BIDHI3_MS": "ayxfi",
        "BIDHI4_MS": "fwubr",
        "BIDHI5_MS": "cxkph",
        "BIDLO1_MS": "qvzjs",
        "BIDLO2_MS": "npdjd",
        "BIDLO3_MS": "deppg",
        "BIDLO4_MS": "pysxy",
        "BIDLO5_MS": "oavlz",
        "MIDHI1_MS": "vxipt",
        "MIDLO1_MS": "ouaxq",
        "BID_HR_MS": "swcij"
    },
    {
        "PROD_PERM": 39,
        "RDNDISPLAY": 41,
        "DSPLY_NAME": "xmtoh",
        "TIMACT": "ilpwt",
        "NETCHNG_1": 0.62,
        "HIGH_1": 0.21,
        "LOW_1": 0.27,
        "CURRENCY": "gyoju",
        "ACTIV_DATE": "ccijm",
        "OPEN_PRC": 0.37,
        "HST_CLOSE": 0.1,
        "BID": 0.2,
        "BID_1": 0.25,
        "BID_2": 0.46,
        "ASK": 0.38,
        "ASK_1": 0.28,
        "ASK_2": 0.27,
        "ACVOL_1": 64,
        "TRD_UNITS": "rjaxv",
        "PCTCHNG": 0.29,
        "OPEN_BID": 0.95,
        "OPEN_ASK": 0.7,
        "CLOSE_BID": 0.93,
        "CLOSE_ASK": 0.83,
        "NUM_MOVES": 92,
        "OFFCL_CODE": "jvuyh",
        "HSTCLSDATE": "wjuik",
        "YRHIGH": 0.41,
        "YRLOW": 0.86,
        "BCKGRNDPAG": "hxlkb",
        "BID_NET_CH": 0.69,
        "BID_TICK_1": "eixit",
        "MID_PRICE": 0.24,
        "MID_NET_CH": 0.56,
        "MID_CLOSE": 0.76,
        "HIGHTP_1": "tdkht",
        "LOWTP_1": "olwxv",
        "BID_HIGH_1": 0.55,
        "BID_LOW_1": 0.74,
        "YRBIDHIGH": 0.75,
        "YRBIDLOW": 0.06,
        "HST_CLSBID": 0.79,
        "HSTCLBDDAT": "sepfj",
        "NUM_BIDS": 7,
        "RECORDTYPE": 1,
        "ACT_TP_1": "buien",
        "ACT_TP_2": "gnlwj",
        "ACT_TP_3": "uvbjl",
        "SEC_ACT_1": 0.64,
        "SEC_ACT_2": 0.1,
        "SEC_ACT_3": 0.48,
        "SC_ACT_TP1": "gfugh",
        "SC_ACT_TP2": "vorxd",
        "SC_ACT_TP3": "fxxwq",
        "OPEN_TIME": "wkwlr",
        "HIGH_TIME": "qtybj",
        "LOW_TIME": "nopki",
        "YRHIGHDAT": "mozaa",
        "YRLOWDAT": "yxlyl",
        "IRGPRC": 0.87,
        "TIMCOR": "nkiml",
        "PRIMACT_1": 0.65,
        "PRIMACT_2": 0.92,
        "PRIMACT_3": 0.46,
        "BASE_CCY": "udyta",
        "BCAST_REF": "akfsl",
        "CROSS_SC": "glzrz",
        "DLG_CODE1": "rgqla",
        "DLG_CODE2": "sfqoc",
        "DLG_CODE3": "uvklq",
        "CTBTR_1": "zsnrs",
        "CTBTR_2": "tbyzh",
        "CTBTR_3": "wcjjj",
        "CTB_LOC1": "bvdxs",
        "CTB_LOC2": "jvcqq",
        "CTB_LOC3": "imhcn",
        "CTB_PAGE1": "crqsz",
        "CTB_PAGE2": "bfxwe",
        "CTB_PAGE3": "ceybk",
        "VALUE_DT1": "xoawq",
        "VALUE_DT2": "kgstt",
        "VALUE_DT3": "kwksl",
        "SEC_HIGH": 0.61,
        "SEC_HI_TP": "aobpv",
        "SEC_LOW": 0.94,
        "SEC_LO_TP": "otvxk",
        "OPEN_TYPE": "zqtey",
        "CLOSE_TYPE": "ywlhx",
        "BKGD_REF": "aiiqg",
        "GEN_TEXT16": "brgii",
        "GEN_VAL3": 0.51,
        "GEN_VAL4": 0.53,
        "GV1_TEXT": "clsfu",
        "GV2_TEXT": "ifdiq",
        "GV4_TEXT": "hnrpe",
        "VALUE_TS1": "sevop",
        "VALUE_TS2": "nfepd",
        "VALUE_TS3": "vvmtc",
        "QUOTIM": "wnvkv",
        "GEN_VAL5": 0.9,
        "GEN_VAL6": 0.6,
        "GEN_VAL7": 0.19,
        "GEN_VAL8": 0.49,
        "GEN_VAL9": 0.51,
        "GEN_VAL10": 0.03,
        "GV5_TEXT": "qrzud",
        "GV6_TEXT": "ddlyl",
        "GV7_TEXT": "aqgro",
        "GV8_TEXT": "fbero",
        "GV9_TEXT": "aywfb",
        "GV10_TEXT": "dsakb",
        "GN_TXT16_2": "pwqpp",
        "GV1_TIME": "jqans",
        "PREF_DISP": 84,
        "GN_TXT24_1": "khtno",
        "DSO_ID": 47,
        "RDN_EXCHD2": "tkwuy",
        "PREV_DISP": 58,
        "ASIA_CL_DT": "npgly",
        "ASIA_CLOSE": 0.33,
        "ASIA_HI_TM": "dxyqc",
        "ASIA_HIGH": 0.73,
        "ASIA_LOW": 0.04,
        "ASIA_LW_TM": "wwrbg",
        "ASIA_NETCH": 0.6,
        "ASIA_OP_TM": "mdeux",
        "ASIA_OPEN": 0.79,
        "EURO_CL_DT": "fqgxy",
        "EURO_CLOSE": 0.6,
        "EURO_HI_TM": "rabke",
        "EURO_HIGH": 0.27,
        "EURO_LOW": 0.63,
        "EURO_LW_TM": "madox",
        "EURO_NETCH": 0.89,
        "EURO_OP_TM": "xuqzp",
        "EURO_OPEN": 0.96,
        "US_CL_DT": "ebbqh",
        "US_CLOSE": 0.55,
        "US_HI_TM": "ymqde",
        "US_HIGH": 0.98,
        "US_LOW": 0.43,
        "US_LW_TM": "ujqjd",
        "US_NETCH": 0.56,
        "US_OP_TM": "cpzrp",
        "US_OPEN": 0.13,
        "ASK_SPREAD": 0.29,
        "BID_SPREAD": 0.74,
        "MID_SPREAD": 0.57,
        "MONTH_HIGH": 0.29,
        "MONTH_LOW": 0.83,
        "PCTCHG_3M": 0.59,
        "PCTCHG_6M": 0.82,
        "PCTCHG_MTD": 0.49,
        "PCTCHG_YTD": 0.52,
        "QUOTE_DATE": "miljl",
        "WEEK_HIGH": 0.28,
        "WEEK_LOW": 0.08,
        "ASK_HIGH_1": 0.96,
        "ASK_HI_TME": "xsrnk",
        "ASK_LOW_1": 0.81,
        "ASK_LO_TME": "vzrfs",
        "BID_ASK_DT": "ufbvu",
        "HIGH_2": 0.56,
        "HIGH_3": 0.23,
        "HIGH_4": 1.0,
        "HIGH_5": 0.63,
        "HIGH_TIME2": "wrfkg",
        "HIGH_TIME3": "qsmrc",
        "HIGH_TIME4": "gwaix",
        "HIGH_TIME5": "mrxfh",
        "LOW_2": 0.42,
        "LOW_3": 0.95,
        "LOW_4": 0.89,
        "LOW_5": 0.13,
        "LOW_TIME2": "gsmky",
        "LOW_TIME3": "oxvoy",
        "LOW_TIME4": "lpdxw",
        "LOW_TIME5": "vrypu",
        "SCALING": "qihpg",
        "START_DT": "kndsf",
        "WKHI_DT": "vkpzw",
        "WKLO_DT": "rvfej",
        "MTHHI_DT": "iixfl",
        "MTHLO_DT": "dsuic",
        "QUOTIM_MS": 2,
        "MID_HIGH": 0.4,
        "MID_LOW": 0.08,
        "MID_HTIM": "gocpm",
        "MID_LTIM": "vmubs",
        "MID_OPEN": 0.41,
        "CONTEXT_ID": 31,
        "BID_HIGH_2": 0.36,
        "BID_HIGH_3": 0.82,
        "BID_HIGH_4": 0.82,
        "BID_HIGH_5": 0.02,
        "BID_LOW_2": 0.9,
        "BID_LOW_3": 0.97,
        "BID_LOW_4": 0.27,
        "BID_LOW_5": 0.2,
        "ASK_HIGH_2": 0.45,
        "ASK_HIGH_3": 0.62,
        "ASK_HIGH_4": 0.65,
        "ASK_HIGH_5": 0.49,
        "ASK_LOW_2": 0.39,
        "ASK_LOW_3": 0.51,
        "ASK_LOW_4": 0.62,
        "ASK_LOW_5": 0.83,
        "PRV_BID_H": 0.2,
        "PRV_ASK_H": 0.03,
        "PRV_BID_L": 0.48,
        "PRV_ASK_L": 0.32,
        "DDS_DSO_ID": 98,
        "BR_LINK1": null,
        "BR_LINK2": null,
        "BR_LINK3": null,
        "SPS_SP_RIC": "bmhly",
        "QUOTIM_2": "kksmx",
        "QUOTIM_3": "rmrwg",
        "QUOTE_DT2": "uomfw",
        "QUOTE_DT3": "mzana",
        "ASKYRHIDAT": "heisl",
        "ASKYRLODAT": "podup",
        "BIDYRHIDAT": "pyodp",
        "BIDYRLODAT": "xolof",
        "ASIABAC_DT": "odyiu",
        "EUBAC_DT": "nzaza",
        "USBAC_DT": "doagc",
        "HST_NUMBID": 91,
        "ASK_FWDOR": null,
        "BID_FWDOR": null,
        "AMERCL_ASK": 0.81,
        "AMERCL_BID": 0.03,
        "AMERHI_ASK": 0.97,
        "AMERHI_BID": 0.95,
        "AMERLO_ASK": 0.21,
        "AMERLO_BID": 0.71,
        "AMEROP_ASK": 0.23,
        "AMEROP_BID": 0.06,
        "ASIACL_ASK": 0.78,
        "ASIACL_BID": 0.87,
        "ASIAHI_ASK": 0.45,
        "ASIAHI_BID": 0.56,
        "ASIALO_ASK": 0.11,
        "ASIALO_BID": 0.64,
        "ASIAOP_ASK": 0.92,
        "ASIAOP_BID": 0.45,
        "BIDPCTCHNG": 0.15,
        "EURCL_ASK": 0.61,
        "EURCL_BID": 1.0,
        "EURHI_ASK": 0.73,
        "EURHI_BID": 0.02,
        "EURLO_ASK": 0.35,
        "EURLO_BID": 0.08,
        "EUROP_ASK": 0.4,
        "EUROP_BID": 0.09,
        "HST_HIMID": 0.22,
        "HST_LOMID": 0.93,
        "HST_OPNASK": 0.06,
        "HST_OPNBID": 0.82,
        "YRASKHIGH": 0.91,
        "YRASKLOW": 0.96,
        "ASIA_BNC": 0.46,
        "EURO_BNC": 0.99,
        "MTH_ASK_LO": 0.61,
        "MTH_BID_HI": 0.36,
        "US_BNC": 0.13,
        "WK_ASK_LO": 0.24,
        "WK_BID_HI": 0.84,
        "BID_HOURLY": 0.14,
        "RCS_AS_CL2": "kccez",
        "MTH_ALO_DT": "xqvdc",
        "MTH_BHI_DT": "mwmsv",
        "WK_ALO_DT": "tznxl",
        "WK_BHI_DT": "uoavt",
        "FXMM_TYPE": "djvea",
        "ASIA_AH_MS": "gjyvw",
        "ASIA_AL_MS": "bscef",
        "ASIA_AO_MS": "nlbxt",
        "ASIA_BH_MS": "nkudw",
        "ASIA_BL_MS": "tcwpw",
        "ASIA_BO_MS": "lsabz",
        "EURO_AH_MS": "gjnoq",
        "EURO_AL_MS": "uekaf",
        "EURO_AO_MS": "iehyw",
        "EURO_BH_MS": "mbkcz",
        "EURO_BL_MS": "iodtw",
        "EURO_BO_MS": "awcso",
        "US_AH_MS": "illjn",
        "US_AL_MS": "alxyv",
        "US_AO_MS": "tzeia",
        "US_BH_MS": "niiem",
        "US_BL_MS": "rybyr",
        "US_BO_MS": "fytqf",
        "OPN_BID_MS": "bsagh",
        "ASKHI1_MS": "afopa",
        "ASKHI2_MS": "xjgjf",
        "ASKHI3_MS": "xegls",
        "ASKHI4_MS": "pwocb",
        "ASKHI5_MS": "ddyza",
        "ASKLO1_MS": "vbsdh",
        "ASKLO2_MS": "vjdsb",
        "ASKLO3_MS": "giiin",
        "ASKLO4_MS": "gkley",
        "ASKLO5_MS": "roeub",
        "BIDHI1_MS": "mrfbt",
        "BIDHI2_MS": "mdvxp",
        "BIDHI3_MS": "gkxde",
        "BIDHI4_MS": "xikra",
        "BIDHI5_MS": "snzqj",
        "BIDLO1_MS": "ffvps",
        "BIDLO2_MS": "rvsvz",
        "BIDLO3_MS": "cwhxo",
        "BIDLO4_MS": "hzuei",
        "BIDLO5_MS": "gyukc",
        "MIDHI1_MS": "byhps",
        "MIDLO1_MS": "jfppn",
        "BID_HR_MS": "uhggh"
    }
]